[
  {
    "alpha_hill": 1.073045909975794,
    "xi": 0.8689702190782991,
    "W1": 0.09054935294499271,
    "n_lifetimes": 447,
    "family": "levy_alpha_1.2",
    "rep": 0
  },
  {
    "alpha_hill": 1.1095789647647725,
    "xi": 0.8667977292572592,
    "W1": 0.079352745936667,
    "n_lifetimes": 502,
    "family": "levy_alpha_1.2",
    "rep": 1
  },
  {
    "alpha_hill": 1.0738768616526897,
    "xi": 0.85186685960282,
    "W1": 0.07398429177363028,
    "n_lifetimes": 500,
    "family": "levy_alpha_1.2",
    "rep": 2
  },
  {
    "alpha_hill": 1.142491672626031,
    "xi": 0.7350749896697072,
    "W1": 0.07978587594173868,
    "n_lifetimes": 465,
    "family": "levy_alpha_1.2",
    "rep": 3
  },
  {
    "alpha_hill": 1.3961970218047592,
    "xi": 0.5483604022754833,
    "W1": 0.05005134764526509,
    "n_lifetimes": 525,
    "family": "levy_alpha_1.2",
    "rep": 4
  },
  {
    "alpha_hill": 1.2138326263964552,
    "xi": 0.7322477866103508,
    "W1": 0.11048776462567163,
    "n_lifetimes": 503,
    "family": "levy_alpha_1.2",
    "rep": 5
  },
  {
    "alpha_hill": 0.866386854134473,
    "xi": 1.041721758580652,
    "W1": 0.10688367635211055,
    "n_lifetimes": 403,
    "family": "levy_alpha_1.2",
    "rep": 6
  },
  {
    "alpha_hill": 1.140546792407428,
    "xi": 0.8373237743189941,
    "W1": 0.11009554901950291,
    "n_lifetimes": 383,
    "family": "levy_alpha_1.2",
    "rep": 7
  },
  {
    "alpha_hill": 0.9576713995463493,
    "xi": 0.9699653395692672,
    "W1": 0.11462094922748706,
    "n_lifetimes": 495,
    "family": "levy_alpha_1.2",
    "rep": 8
  },
  {
    "alpha_hill": 1.0219249589307027,
    "xi": 0.9472943860939506,
    "W1": 0.11199151278007513,
    "n_lifetimes": 329,
    "family": "levy_alpha_1.2",
    "rep": 9
  },
  {
    "alpha_hill": 1.199938227495006,
    "xi": 0.7438156686943181,
    "W1": 0.09618690465850772,
    "n_lifetimes": 481,
    "family": "levy_alpha_1.2",
    "rep": 10
  },
  {
    "alpha_hill": 1.0402899948643851,
    "xi": 1.0125487470935992,
    "W1": 0.06510611713327555,
    "n_lifetimes": 488,
    "family": "levy_alpha_1.2",
    "rep": 11
  },
  {
    "alpha_hill": 0.9566272347545676,
    "xi": 1.0916822706655778,
    "W1": 0.11719291961228592,
    "n_lifetimes": 358,
    "family": "levy_alpha_1.2",
    "rep": 12
  },
  {
    "alpha_hill": 1.1432742045753497,
    "xi": 0.7893413444999303,
    "W1": 0.09151970601456624,
    "n_lifetimes": 502,
    "family": "levy_alpha_1.2",
    "rep": 13
  },
  {
    "alpha_hill": 1.0610167409498144,
    "xi": 0.9090284363679275,
    "W1": 0.11644868389962176,
    "n_lifetimes": 399,
    "family": "levy_alpha_1.2",
    "rep": 14
  },
  {
    "alpha_hill": 1.1252832889952202,
    "xi": 0.8407375516657792,
    "W1": 0.05340554959142813,
    "n_lifetimes": 510,
    "family": "levy_alpha_1.2",
    "rep": 15
  },
  {
    "alpha_hill": 1.0725639720000189,
    "xi": 0.9580543875141976,
    "W1": 0.11463399946316853,
    "n_lifetimes": 226,
    "family": "levy_alpha_1.2",
    "rep": 16
  },
  {
    "alpha_hill": 0.9690571339955932,
    "xi": 0.859408306143584,
    "W1": 0.10599487693679603,
    "n_lifetimes": 487,
    "family": "levy_alpha_1.2",
    "rep": 17
  },
  {
    "alpha_hill": 0.9666394269357027,
    "xi": 0.866580615815497,
    "W1": 0.09794787949355738,
    "n_lifetimes": 489,
    "family": "levy_alpha_1.2",
    "rep": 18
  },
  {
    "alpha_hill": 1.2642015343444688,
    "xi": 0.7306305837827687,
    "W1": 0.09283371670976084,
    "n_lifetimes": 506,
    "family": "levy_alpha_1.2",
    "rep": 19
  },
  {
    "alpha_hill": 1.0910752876779648,
    "xi": 0.9563497394846697,
    "W1": 0.08278570042045767,
    "n_lifetimes": 490,
    "family": "levy_alpha_1.2",
    "rep": 20
  },
  {
    "alpha_hill": 1.2401045303782774,
    "xi": 0.5543395520508083,
    "W1": 0.09576443273846158,
    "n_lifetimes": 507,
    "family": "levy_alpha_1.2",
    "rep": 21
  },
  {
    "alpha_hill": 1.1015724005166672,
    "xi": 0.8334449122769001,
    "W1": 0.09070311430258945,
    "n_lifetimes": 488,
    "family": "levy_alpha_1.2",
    "rep": 22
  },
  {
    "alpha_hill": 1.082200735081105,
    "xi": 0.7795437529129708,
    "W1": 0.11227225744570109,
    "n_lifetimes": 456,
    "family": "levy_alpha_1.2",
    "rep": 23
  },
  {
    "alpha_hill": 1.1577185226309128,
    "xi": 0.8036775495640085,
    "W1": 0.1068598406758147,
    "n_lifetimes": 503,
    "family": "levy_alpha_1.2",
    "rep": 24
  },
  {
    "alpha_hill": 1.1254713216626646,
    "xi": 0.7895679926300126,
    "W1": 0.09470233363507752,
    "n_lifetimes": 511,
    "family": "levy_alpha_1.2",
    "rep": 25
  },
  {
    "alpha_hill": 1.1243433973182535,
    "xi": 0.8097425934360818,
    "W1": 0.07518155868804043,
    "n_lifetimes": 510,
    "family": "levy_alpha_1.2",
    "rep": 26
  },
  {
    "alpha_hill": 1.033039134542436,
    "xi": 0.7612040364485155,
    "W1": 0.08036051448857946,
    "n_lifetimes": 475,
    "family": "levy_alpha_1.2",
    "rep": 27
  },
  {
    "alpha_hill": 0.9889358874579381,
    "xi": 1.0997709199166303,
    "W1": 0.0780222277110909,
    "n_lifetimes": 478,
    "family": "levy_alpha_1.2",
    "rep": 28
  },
  {
    "alpha_hill": 1.1060250881423332,
    "xi": 0.7696463919711511,
    "W1": 0.11604825620999443,
    "n_lifetimes": 475,
    "family": "levy_alpha_1.2",
    "rep": 29
  },
  {
    "alpha_hill": 0.8571932978554351,
    "xi": 1.2788493419868792,
    "W1": 0.11519138162867637,
    "n_lifetimes": 254,
    "family": "levy_alpha_1.2",
    "rep": 30
  },
  {
    "alpha_hill": 1.1852475672643612,
    "xi": 0.725332613088983,
    "W1": 0.10537678052306776,
    "n_lifetimes": 446,
    "family": "levy_alpha_1.2",
    "rep": 31
  },
  {
    "alpha_hill": 1.1572833399230544,
    "xi": 0.8251826056160603,
    "W1": 0.08592195987863624,
    "n_lifetimes": 494,
    "family": "levy_alpha_1.2",
    "rep": 32
  },
  {
    "alpha_hill": 1.0747057047299624,
    "xi": 0.7842598604398903,
    "W1": 0.09590236110314732,
    "n_lifetimes": 422,
    "family": "levy_alpha_1.2",
    "rep": 33
  },
  {
    "alpha_hill": 1.0503866171612868,
    "xi": 0.9223935043314494,
    "W1": 0.11023272272631134,
    "n_lifetimes": 439,
    "family": "levy_alpha_1.2",
    "rep": 34
  },
  {
    "alpha_hill": 1.1266361075204006,
    "xi": 0.7933301109648894,
    "W1": 0.10137782964064951,
    "n_lifetimes": 499,
    "family": "levy_alpha_1.2",
    "rep": 35
  },
  {
    "alpha_hill": 1.1817985031692744,
    "xi": 0.8983982180645472,
    "W1": 0.10388430807700363,
    "n_lifetimes": 505,
    "family": "levy_alpha_1.2",
    "rep": 36
  },
  {
    "alpha_hill": 0.9449656654710518,
    "xi": 1.1255055558778286,
    "W1": 0.11831165757475393,
    "n_lifetimes": 191,
    "family": "levy_alpha_1.2",
    "rep": 37
  },
  {
    "alpha_hill": 1.1223218827281887,
    "xi": 0.8746595241250765,
    "W1": 0.10930937960759275,
    "n_lifetimes": 444,
    "family": "levy_alpha_1.2",
    "rep": 38
  },
  {
    "alpha_hill": 1.220820904212771,
    "xi": 0.7304713520245458,
    "W1": 0.09515967372663137,
    "n_lifetimes": 479,
    "family": "levy_alpha_1.2",
    "rep": 39
  },
  {
    "alpha_hill": 1.1910918941075859,
    "xi": 0.629981265979104,
    "W1": 0.1065802345674706,
    "n_lifetimes": 477,
    "family": "levy_alpha_1.2",
    "rep": 40
  },
  {
    "alpha_hill": 1.1389888095787997,
    "xi": 0.7178740391859935,
    "W1": 0.07076167228119287,
    "n_lifetimes": 499,
    "family": "levy_alpha_1.2",
    "rep": 41
  },
  {
    "alpha_hill": 1.0639237535047386,
    "xi": 0.8530054601818753,
    "W1": 0.10250131146868528,
    "n_lifetimes": 444,
    "family": "levy_alpha_1.2",
    "rep": 42
  },
  {
    "alpha_hill": 0.8906387116978294,
    "xi": 0.9670792984075113,
    "W1": 0.0857178275568818,
    "n_lifetimes": 501,
    "family": "levy_alpha_1.2",
    "rep": 43
  },
  {
    "alpha_hill": 0.9543621552928938,
    "xi": 0.8643023649715569,
    "W1": 0.11588778983162397,
    "n_lifetimes": 470,
    "family": "levy_alpha_1.2",
    "rep": 44
  },
  {
    "alpha_hill": 1.0191625998712948,
    "xi": 0.9236166771122961,
    "W1": 0.05801446952587745,
    "n_lifetimes": 521,
    "family": "levy_alpha_1.2",
    "rep": 45
  },
  {
    "alpha_hill": 0.9937150799030486,
    "xi": 0.8070627210813952,
    "W1": 0.11161419484991324,
    "n_lifetimes": 469,
    "family": "levy_alpha_1.2",
    "rep": 46
  },
  {
    "alpha_hill": 1.024203549424969,
    "xi": 0.9322788626442514,
    "W1": 0.09409245861659772,
    "n_lifetimes": 469,
    "family": "levy_alpha_1.2",
    "rep": 47
  },
  {
    "alpha_hill": 1.0367976500284664,
    "xi": 0.8964945011612995,
    "W1": 0.11870879456645128,
    "n_lifetimes": 429,
    "family": "levy_alpha_1.2",
    "rep": 48
  },
  {
    "alpha_hill": 1.0152174202806685,
    "xi": 0.8501455907631328,
    "W1": 0.07845430722879881,
    "n_lifetimes": 495,
    "family": "levy_alpha_1.2",
    "rep": 49
  },
  {
    "alpha_hill": 1.546674684676044,
    "xi": 0.491042859340508,
    "W1": 0.052014120299295266,
    "n_lifetimes": 512,
    "family": "levy_alpha_1.5",
    "rep": 0
  },
  {
    "alpha_hill": 1.2714721182998026,
    "xi": 0.6207751828231722,
    "W1": 0.07016857374899464,
    "n_lifetimes": 504,
    "family": "levy_alpha_1.5",
    "rep": 1
  },
  {
    "alpha_hill": 1.3797439921119872,
    "xi": 0.5720051435289747,
    "W1": 0.09200704265423176,
    "n_lifetimes": 495,
    "family": "levy_alpha_1.5",
    "rep": 2
  },
  {
    "alpha_hill": 1.4537339917447505,
    "xi": 0.41182330028833314,
    "W1": 0.061169946384250426,
    "n_lifetimes": 503,
    "family": "levy_alpha_1.5",
    "rep": 3
  },
  {
    "alpha_hill": 1.3814191104058064,
    "xi": 0.625471314389092,
    "W1": 0.07984568352168007,
    "n_lifetimes": 508,
    "family": "levy_alpha_1.5",
    "rep": 4
  },
  {
    "alpha_hill": 1.1594281777114073,
    "xi": 0.7959376646968711,
    "W1": 0.11068861281087197,
    "n_lifetimes": 475,
    "family": "levy_alpha_1.5",
    "rep": 5
  },
  {
    "alpha_hill": 1.3249158641520262,
    "xi": 0.5687768039736039,
    "W1": 0.09871539264062634,
    "n_lifetimes": 497,
    "family": "levy_alpha_1.5",
    "rep": 6
  },
  {
    "alpha_hill": 1.255291067413269,
    "xi": 0.5713195623744434,
    "W1": 0.09603623909333255,
    "n_lifetimes": 493,
    "family": "levy_alpha_1.5",
    "rep": 7
  },
  {
    "alpha_hill": 1.6623246649961754,
    "xi": 0.464499139845988,
    "W1": 0.11825069197302318,
    "n_lifetimes": 509,
    "family": "levy_alpha_1.5",
    "rep": 8
  },
  {
    "alpha_hill": 1.2503880800339118,
    "xi": 0.7443479703443878,
    "W1": 0.039621060446860985,
    "n_lifetimes": 495,
    "family": "levy_alpha_1.5",
    "rep": 9
  },
  {
    "alpha_hill": 1.2797597774513447,
    "xi": 0.7775152188088337,
    "W1": 0.06685301588926063,
    "n_lifetimes": 476,
    "family": "levy_alpha_1.5",
    "rep": 10
  },
  {
    "alpha_hill": 1.5014431711409677,
    "xi": 0.5956853254182215,
    "W1": 0.06933418914815781,
    "n_lifetimes": 478,
    "family": "levy_alpha_1.5",
    "rep": 11
  },
  {
    "alpha_hill": 1.418173876353671,
    "xi": 0.457863026153084,
    "W1": 0.023099934707279213,
    "n_lifetimes": 510,
    "family": "levy_alpha_1.5",
    "rep": 12
  },
  {
    "alpha_hill": 1.4007702317991197,
    "xi": 0.6088910150770668,
    "W1": 0.051858689396990634,
    "n_lifetimes": 503,
    "family": "levy_alpha_1.5",
    "rep": 13
  },
  {
    "alpha_hill": 1.443853593532309,
    "xi": 0.46035884647312164,
    "W1": 0.07976392660575851,
    "n_lifetimes": 509,
    "family": "levy_alpha_1.5",
    "rep": 14
  },
  {
    "alpha_hill": 1.1336315667209407,
    "xi": 0.9155987734266536,
    "W1": 0.08882194047049663,
    "n_lifetimes": 489,
    "family": "levy_alpha_1.5",
    "rep": 15
  },
  {
    "alpha_hill": 1.2286837435936704,
    "xi": 0.6139863631914404,
    "W1": 0.08020758871450684,
    "n_lifetimes": 513,
    "family": "levy_alpha_1.5",
    "rep": 16
  },
  {
    "alpha_hill": 1.5944332933259173,
    "xi": 0.6332926063292197,
    "W1": 0.10377015987023393,
    "n_lifetimes": 510,
    "family": "levy_alpha_1.5",
    "rep": 17
  },
  {
    "alpha_hill": 1.3410429310018552,
    "xi": 0.6633554575648251,
    "W1": 0.10051335720579366,
    "n_lifetimes": 503,
    "family": "levy_alpha_1.5",
    "rep": 18
  },
  {
    "alpha_hill": 1.2648459236527088,
    "xi": 0.8396510776727535,
    "W1": 0.09989845072474081,
    "n_lifetimes": 512,
    "family": "levy_alpha_1.5",
    "rep": 19
  },
  {
    "alpha_hill": 1.2833034059325918,
    "xi": 0.6303627063607661,
    "W1": 0.08129157523889348,
    "n_lifetimes": 497,
    "family": "levy_alpha_1.5",
    "rep": 20
  },
  {
    "alpha_hill": 1.2032436689058899,
    "xi": 0.7756873551950254,
    "W1": 0.04813843924078552,
    "n_lifetimes": 499,
    "family": "levy_alpha_1.5",
    "rep": 21
  },
  {
    "alpha_hill": 1.4812412395107157,
    "xi": 0.7098568486546264,
    "W1": 0.07555202636604888,
    "n_lifetimes": 492,
    "family": "levy_alpha_1.5",
    "rep": 22
  },
  {
    "alpha_hill": 1.401517265202647,
    "xi": 0.5384369814285298,
    "W1": 0.09340440323383123,
    "n_lifetimes": 484,
    "family": "levy_alpha_1.5",
    "rep": 23
  },
  {
    "alpha_hill": 1.347828341580656,
    "xi": 0.6430185453509136,
    "W1": 0.04611822233973659,
    "n_lifetimes": 501,
    "family": "levy_alpha_1.5",
    "rep": 24
  },
  {
    "alpha_hill": 1.2234350971991013,
    "xi": 0.8294272626265223,
    "W1": 0.08294072105236217,
    "n_lifetimes": 502,
    "family": "levy_alpha_1.5",
    "rep": 25
  },
  {
    "alpha_hill": 1.3562671336790213,
    "xi": 0.744287277713326,
    "W1": 0.05161897634751011,
    "n_lifetimes": 502,
    "family": "levy_alpha_1.5",
    "rep": 26
  },
  {
    "alpha_hill": 1.2084234179987599,
    "xi": 0.7481807830771009,
    "W1": 0.09382056895489452,
    "n_lifetimes": 495,
    "family": "levy_alpha_1.5",
    "rep": 27
  },
  {
    "alpha_hill": 1.5616317839677587,
    "xi": 0.5678283293896178,
    "W1": 0.057403602694785505,
    "n_lifetimes": 483,
    "family": "levy_alpha_1.5",
    "rep": 28
  },
  {
    "alpha_hill": 1.3238308948407351,
    "xi": 0.45685947748019584,
    "W1": 0.10561646212599093,
    "n_lifetimes": 492,
    "family": "levy_alpha_1.5",
    "rep": 29
  },
  {
    "alpha_hill": 1.2691682615869828,
    "xi": 0.6516088828732247,
    "W1": 0.07149813118343908,
    "n_lifetimes": 498,
    "family": "levy_alpha_1.5",
    "rep": 30
  },
  {
    "alpha_hill": 1.4067775771620974,
    "xi": 0.6520665803058163,
    "W1": 0.12466717578547816,
    "n_lifetimes": 473,
    "family": "levy_alpha_1.5",
    "rep": 31
  },
  {
    "alpha_hill": 1.499356952723688,
    "xi": 0.6709813294383582,
    "W1": 0.050229566135051126,
    "n_lifetimes": 525,
    "family": "levy_alpha_1.5",
    "rep": 32
  },
  {
    "alpha_hill": 1.3874900453546213,
    "xi": 0.739544896893663,
    "W1": 0.06516953456995686,
    "n_lifetimes": 501,
    "family": "levy_alpha_1.5",
    "rep": 33
  },
  {
    "alpha_hill": 1.3904583737545775,
    "xi": 0.5786184763743659,
    "W1": 0.04363039760938456,
    "n_lifetimes": 513,
    "family": "levy_alpha_1.5",
    "rep": 34
  },
  {
    "alpha_hill": 1.3284341380491422,
    "xi": 0.6240666864085684,
    "W1": 0.06925972514460921,
    "n_lifetimes": 479,
    "family": "levy_alpha_1.5",
    "rep": 35
  },
  {
    "alpha_hill": 1.530787312537397,
    "xi": 0.5202127185616219,
    "W1": 0.08821531762591599,
    "n_lifetimes": 491,
    "family": "levy_alpha_1.5",
    "rep": 36
  },
  {
    "alpha_hill": 1.3154387829349343,
    "xi": 0.6587430726519329,
    "W1": 0.0805080269038418,
    "n_lifetimes": 494,
    "family": "levy_alpha_1.5",
    "rep": 37
  },
  {
    "alpha_hill": 1.337768957772848,
    "xi": 0.6045875835942398,
    "W1": 0.08070818089044483,
    "n_lifetimes": 493,
    "family": "levy_alpha_1.5",
    "rep": 38
  },
  {
    "alpha_hill": 1.2172197165301573,
    "xi": 0.6951089190241297,
    "W1": 0.06381396356297664,
    "n_lifetimes": 476,
    "family": "levy_alpha_1.5",
    "rep": 39
  },
  {
    "alpha_hill": 1.3835467718228922,
    "xi": 0.6672632027024354,
    "W1": 0.10960332228677994,
    "n_lifetimes": 481,
    "family": "levy_alpha_1.5",
    "rep": 40
  },
  {
    "alpha_hill": 1.39073171803226,
    "xi": 0.6102782646446863,
    "W1": 0.09868223520751684,
    "n_lifetimes": 459,
    "family": "levy_alpha_1.5",
    "rep": 41
  },
  {
    "alpha_hill": 1.3346235058597373,
    "xi": 0.7639706498746646,
    "W1": 0.06614297600231964,
    "n_lifetimes": 506,
    "family": "levy_alpha_1.5",
    "rep": 42
  },
  {
    "alpha_hill": 1.2330128395244062,
    "xi": 0.7152596190644915,
    "W1": 0.08906705541008506,
    "n_lifetimes": 508,
    "family": "levy_alpha_1.5",
    "rep": 43
  },
  {
    "alpha_hill": 1.2844754602525987,
    "xi": 0.5725213832003954,
    "W1": 0.037218179965634986,
    "n_lifetimes": 487,
    "family": "levy_alpha_1.5",
    "rep": 44
  },
  {
    "alpha_hill": 1.3929120630981178,
    "xi": 0.5957642506167071,
    "W1": 0.0543307779657064,
    "n_lifetimes": 499,
    "family": "levy_alpha_1.5",
    "rep": 45
  },
  {
    "alpha_hill": 1.579368751933587,
    "xi": 0.49626381355356064,
    "W1": 0.07004771225917279,
    "n_lifetimes": 504,
    "family": "levy_alpha_1.5",
    "rep": 46
  },
  {
    "alpha_hill": 1.299500728687333,
    "xi": 0.6558043531921933,
    "W1": 0.055819340813932646,
    "n_lifetimes": 478,
    "family": "levy_alpha_1.5",
    "rep": 47
  },
  {
    "alpha_hill": 1.4342654456794328,
    "xi": 0.6847659487042472,
    "W1": 0.05962203114444827,
    "n_lifetimes": 497,
    "family": "levy_alpha_1.5",
    "rep": 48
  },
  {
    "alpha_hill": 1.1067084928261954,
    "xi": 0.8430236066852643,
    "W1": 0.0919255937383206,
    "n_lifetimes": 514,
    "family": "levy_alpha_1.5",
    "rep": 49
  },
  {
    "alpha_hill": 1.6569794363808144,
    "xi": 0.4613984030958715,
    "W1": 0.07681451446199541,
    "n_lifetimes": 512,
    "family": "levy_alpha_1.8",
    "rep": 0
  },
  {
    "alpha_hill": 1.631901114017493,
    "xi": 0.5198426489676016,
    "W1": 0.07224062814726906,
    "n_lifetimes": 510,
    "family": "levy_alpha_1.8",
    "rep": 1
  },
  {
    "alpha_hill": 1.3754246446578395,
    "xi": 0.6635724375452038,
    "W1": 0.026220672419474907,
    "n_lifetimes": 498,
    "family": "levy_alpha_1.8",
    "rep": 2
  },
  {
    "alpha_hill": 1.8372335975331604,
    "xi": 0.3742329600127831,
    "W1": 0.04417768125514862,
    "n_lifetimes": 503,
    "family": "levy_alpha_1.8",
    "rep": 3
  },
  {
    "alpha_hill": 1.4812517791333943,
    "xi": 0.5954527473977131,
    "W1": 0.015571104554531782,
    "n_lifetimes": 510,
    "family": "levy_alpha_1.8",
    "rep": 4
  },
  {
    "alpha_hill": 1.5268594371765678,
    "xi": 0.4826909601154348,
    "W1": 0.04184970465888315,
    "n_lifetimes": 506,
    "family": "levy_alpha_1.8",
    "rep": 5
  },
  {
    "alpha_hill": 1.7704314494892943,
    "xi": 0.44305914511561084,
    "W1": 0.04896664731659576,
    "n_lifetimes": 492,
    "family": "levy_alpha_1.8",
    "rep": 6
  },
  {
    "alpha_hill": 1.5207529961469226,
    "xi": 0.6371916772542663,
    "W1": 0.01339370777056358,
    "n_lifetimes": 515,
    "family": "levy_alpha_1.8",
    "rep": 7
  },
  {
    "alpha_hill": 1.3374836026102463,
    "xi": 0.5875367758667629,
    "W1": 0.012097120021789545,
    "n_lifetimes": 505,
    "family": "levy_alpha_1.8",
    "rep": 8
  },
  {
    "alpha_hill": 1.474364870849062,
    "xi": 0.6271776218345264,
    "W1": 0.0502924605775361,
    "n_lifetimes": 486,
    "family": "levy_alpha_1.8",
    "rep": 9
  },
  {
    "alpha_hill": 1.7019213678557692,
    "xi": 0.39501952975692367,
    "W1": 0.011872948430846807,
    "n_lifetimes": 493,
    "family": "levy_alpha_1.8",
    "rep": 10
  },
  {
    "alpha_hill": 1.7943420090926134,
    "xi": 0.44768278251974647,
    "W1": 0.022181991476528197,
    "n_lifetimes": 494,
    "family": "levy_alpha_1.8",
    "rep": 11
  },
  {
    "alpha_hill": 1.4717077800259157,
    "xi": 0.3994474783275812,
    "W1": 0.014948087944416027,
    "n_lifetimes": 521,
    "family": "levy_alpha_1.8",
    "rep": 12
  },
  {
    "alpha_hill": 1.5425494934824835,
    "xi": 0.5577977612146834,
    "W1": 0.04747507819916697,
    "n_lifetimes": 503,
    "family": "levy_alpha_1.8",
    "rep": 13
  },
  {
    "alpha_hill": 1.5076507782881445,
    "xi": 0.4821950441778706,
    "W1": 0.03306502632922866,
    "n_lifetimes": 494,
    "family": "levy_alpha_1.8",
    "rep": 14
  },
  {
    "alpha_hill": 1.4013155428276083,
    "xi": 0.6240143967873919,
    "W1": 0.05879977484854306,
    "n_lifetimes": 501,
    "family": "levy_alpha_1.8",
    "rep": 15
  },
  {
    "alpha_hill": 1.4509187912224768,
    "xi": 0.6262334576314138,
    "W1": 0.027051771072619267,
    "n_lifetimes": 497,
    "family": "levy_alpha_1.8",
    "rep": 16
  },
  {
    "alpha_hill": 1.7887760490689455,
    "xi": 0.3589930985380423,
    "W1": 0.011705534766109664,
    "n_lifetimes": 503,
    "family": "levy_alpha_1.8",
    "rep": 17
  },
  {
    "alpha_hill": 1.3761166124001785,
    "xi": 0.5052817784091901,
    "W1": 0.01542883627546528,
    "n_lifetimes": 481,
    "family": "levy_alpha_1.8",
    "rep": 18
  },
  {
    "alpha_hill": 1.427873411340467,
    "xi": 0.5419618720953476,
    "W1": 0.011617218725474148,
    "n_lifetimes": 506,
    "family": "levy_alpha_1.8",
    "rep": 19
  },
  {
    "alpha_hill": 1.5628799773097717,
    "xi": 0.4521104467809986,
    "W1": 0.03501402601884915,
    "n_lifetimes": 502,
    "family": "levy_alpha_1.8",
    "rep": 20
  },
  {
    "alpha_hill": 1.4965744317196177,
    "xi": 0.6373597542621531,
    "W1": 0.059114981174664405,
    "n_lifetimes": 513,
    "family": "levy_alpha_1.8",
    "rep": 21
  },
  {
    "alpha_hill": 1.4908983465100283,
    "xi": 0.6854627804882942,
    "W1": 0.051692570727564266,
    "n_lifetimes": 484,
    "family": "levy_alpha_1.8",
    "rep": 22
  },
  {
    "alpha_hill": 1.452853142661505,
    "xi": 0.5656884777276656,
    "W1": 0.015921618750149483,
    "n_lifetimes": 511,
    "family": "levy_alpha_1.8",
    "rep": 23
  },
  {
    "alpha_hill": 1.841149207211169,
    "xi": 0.2377671289394001,
    "W1": 0.10370064551224187,
    "n_lifetimes": 524,
    "family": "levy_alpha_1.8",
    "rep": 24
  },
  {
    "alpha_hill": 1.6664944889998665,
    "xi": 0.33017060442995577,
    "W1": 0.11516396148782578,
    "n_lifetimes": 501,
    "family": "levy_alpha_1.8",
    "rep": 25
  },
  {
    "alpha_hill": 1.6765864554700054,
    "xi": 0.5560827473655467,
    "W1": 0.011145215476746854,
    "n_lifetimes": 501,
    "family": "levy_alpha_1.8",
    "rep": 26
  },
  {
    "alpha_hill": 1.6043798830080467,
    "xi": 0.48539778554781066,
    "W1": 0.04806906899042798,
    "n_lifetimes": 493,
    "family": "levy_alpha_1.8",
    "rep": 27
  },
  {
    "alpha_hill": 1.4269456253817028,
    "xi": 0.6391280437031006,
    "W1": 0.01706091623680288,
    "n_lifetimes": 520,
    "family": "levy_alpha_1.8",
    "rep": 28
  },
  {
    "alpha_hill": 1.600595579450397,
    "xi": 0.32285886098936967,
    "W1": 0.06374819314490489,
    "n_lifetimes": 501,
    "family": "levy_alpha_1.8",
    "rep": 29
  },
  {
    "alpha_hill": 1.4294478761916163,
    "xi": 0.5418188004089395,
    "W1": 0.039687230223462065,
    "n_lifetimes": 497,
    "family": "levy_alpha_1.8",
    "rep": 30
  },
  {
    "alpha_hill": 1.5010995227748052,
    "xi": 0.5661972810174016,
    "W1": 0.03642207437534972,
    "n_lifetimes": 508,
    "family": "levy_alpha_1.8",
    "rep": 31
  },
  {
    "alpha_hill": 1.2978505986784783,
    "xi": 0.5965378247283601,
    "W1": 0.030904094767191415,
    "n_lifetimes": 495,
    "family": "levy_alpha_1.8",
    "rep": 32
  },
  {
    "alpha_hill": 1.3107691537639503,
    "xi": 0.7757687064505584,
    "W1": 0.01926545503863835,
    "n_lifetimes": 497,
    "family": "levy_alpha_1.8",
    "rep": 33
  },
  {
    "alpha_hill": 1.4714447018159513,
    "xi": 0.5677273537965968,
    "W1": 0.09042086402520334,
    "n_lifetimes": 494,
    "family": "levy_alpha_1.8",
    "rep": 34
  },
  {
    "alpha_hill": 1.6129502128555075,
    "xi": 0.46873875227568373,
    "W1": 0.09417856903443146,
    "n_lifetimes": 509,
    "family": "levy_alpha_1.8",
    "rep": 35
  },
  {
    "alpha_hill": 1.5128480894308174,
    "xi": 0.5734426165915123,
    "W1": 0.019018398642055165,
    "n_lifetimes": 505,
    "family": "levy_alpha_1.8",
    "rep": 36
  },
  {
    "alpha_hill": 1.5859557399976536,
    "xi": 0.5150446542718679,
    "W1": 0.08037882885619257,
    "n_lifetimes": 512,
    "family": "levy_alpha_1.8",
    "rep": 37
  },
  {
    "alpha_hill": 1.587565032765613,
    "xi": 0.36396857835158186,
    "W1": 0.028362701276187507,
    "n_lifetimes": 504,
    "family": "levy_alpha_1.8",
    "rep": 38
  },
  {
    "alpha_hill": 1.5386995094954272,
    "xi": 0.5597712402840447,
    "W1": 0.01941588108864837,
    "n_lifetimes": 508,
    "family": "levy_alpha_1.8",
    "rep": 39
  },
  {
    "alpha_hill": 1.9838731424193976,
    "xi": 0.3986295733729996,
    "W1": 0.051248663448515905,
    "n_lifetimes": 495,
    "family": "levy_alpha_1.8",
    "rep": 40
  },
  {
    "alpha_hill": 1.5852487176054788,
    "xi": 0.44606195273083304,
    "W1": 0.0710997970663415,
    "n_lifetimes": 515,
    "family": "levy_alpha_1.8",
    "rep": 41
  },
  {
    "alpha_hill": 1.492441726525208,
    "xi": 0.5278377325459404,
    "W1": 0.00810687024980189,
    "n_lifetimes": 519,
    "family": "levy_alpha_1.8",
    "rep": 42
  },
  {
    "alpha_hill": 1.450636835114866,
    "xi": 0.5460158948766444,
    "W1": 0.009860772388712169,
    "n_lifetimes": 517,
    "family": "levy_alpha_1.8",
    "rep": 43
  },
  {
    "alpha_hill": 1.5352352635914994,
    "xi": 0.5232952632304282,
    "W1": 0.020877338273880212,
    "n_lifetimes": 515,
    "family": "levy_alpha_1.8",
    "rep": 44
  },
  {
    "alpha_hill": 1.6720873250082142,
    "xi": 0.43861487716788305,
    "W1": 0.05072148871112787,
    "n_lifetimes": 491,
    "family": "levy_alpha_1.8",
    "rep": 45
  },
  {
    "alpha_hill": 1.4900850487312274,
    "xi": 0.3518164716621264,
    "W1": 0.018825364545508986,
    "n_lifetimes": 503,
    "family": "levy_alpha_1.8",
    "rep": 46
  },
  {
    "alpha_hill": 1.5627698778071888,
    "xi": 0.5595710258533455,
    "W1": 0.01287551746046383,
    "n_lifetimes": 499,
    "family": "levy_alpha_1.8",
    "rep": 47
  },
  {
    "alpha_hill": 1.5433864889193867,
    "xi": 0.47046336439288294,
    "W1": 0.04479534750612062,
    "n_lifetimes": 513,
    "family": "levy_alpha_1.8",
    "rep": 48
  },
  {
    "alpha_hill": 1.3134640259476777,
    "xi": 0.7188021309241172,
    "W1": 0.0732845664355181,
    "n_lifetimes": 507,
    "family": "levy_alpha_1.8",
    "rep": 49
  },
  {
    "alpha_hill": 1.7588131125815671,
    "xi": 0.3500267078949756,
    "W1": 0.02846213202282627,
    "n_lifetimes": 485,
    "family": "levy_alpha_2.0",
    "rep": 0
  },
  {
    "alpha_hill": 1.7884939146476426,
    "xi": 0.3558351994216109,
    "W1": 0.02140707543190493,
    "n_lifetimes": 485,
    "family": "levy_alpha_2.0",
    "rep": 1
  },
  {
    "alpha_hill": 1.6199906472053518,
    "xi": 0.5150027954197054,
    "W1": 0.0887752170258925,
    "n_lifetimes": 504,
    "family": "levy_alpha_2.0",
    "rep": 2
  },
  {
    "alpha_hill": 1.551841137887215,
    "xi": 0.4928722612339409,
    "W1": 0.09280353893432805,
    "n_lifetimes": 504,
    "family": "levy_alpha_2.0",
    "rep": 3
  },
  {
    "alpha_hill": 1.7737241765279257,
    "xi": 0.3945315631454589,
    "W1": 0.021027623468201133,
    "n_lifetimes": 487,
    "family": "levy_alpha_2.0",
    "rep": 4
  },
  {
    "alpha_hill": 1.66143782260929,
    "xi": 0.4756932454788319,
    "W1": 0.015796353629859122,
    "n_lifetimes": 507,
    "family": "levy_alpha_2.0",
    "rep": 5
  },
  {
    "alpha_hill": 1.8989826810740071,
    "xi": 0.2764182455383082,
    "W1": 0.014639458752258801,
    "n_lifetimes": 498,
    "family": "levy_alpha_2.0",
    "rep": 6
  },
  {
    "alpha_hill": 2.1685096550064635,
    "xi": 0.1710135839783235,
    "W1": 0.04282456697591766,
    "n_lifetimes": 487,
    "family": "levy_alpha_2.0",
    "rep": 7
  },
  {
    "alpha_hill": 1.7903623353284956,
    "xi": 0.526722097785712,
    "W1": 0.01200276192372143,
    "n_lifetimes": 500,
    "family": "levy_alpha_2.0",
    "rep": 8
  },
  {
    "alpha_hill": 1.7924039152129507,
    "xi": 0.480778388382995,
    "W1": 0.013725866118507984,
    "n_lifetimes": 499,
    "family": "levy_alpha_2.0",
    "rep": 9
  },
  {
    "alpha_hill": 1.6763709051719484,
    "xi": 0.48805917755327655,
    "W1": 0.028466433315346894,
    "n_lifetimes": 507,
    "family": "levy_alpha_2.0",
    "rep": 10
  },
  {
    "alpha_hill": 1.4893807246774213,
    "xi": 0.5331599406958295,
    "W1": 0.012461307443707891,
    "n_lifetimes": 503,
    "family": "levy_alpha_2.0",
    "rep": 11
  },
  {
    "alpha_hill": 1.557422301214153,
    "xi": 0.6250345834924342,
    "W1": 0.008005896392284408,
    "n_lifetimes": 493,
    "family": "levy_alpha_2.0",
    "rep": 12
  },
  {
    "alpha_hill": 1.8055494593404933,
    "xi": 0.3094449600111258,
    "W1": 0.017030551946986563,
    "n_lifetimes": 505,
    "family": "levy_alpha_2.0",
    "rep": 13
  },
  {
    "alpha_hill": 1.822781157915664,
    "xi": 0.4642196202781015,
    "W1": 0.028699401265312976,
    "n_lifetimes": 480,
    "family": "levy_alpha_2.0",
    "rep": 14
  },
  {
    "alpha_hill": 1.5839089354154283,
    "xi": 0.3909123121082903,
    "W1": 0.03571230958090669,
    "n_lifetimes": 486,
    "family": "levy_alpha_2.0",
    "rep": 15
  },
  {
    "alpha_hill": 1.4411320424530507,
    "xi": 0.5770183678715564,
    "W1": 0.007875965635087887,
    "n_lifetimes": 491,
    "family": "levy_alpha_2.0",
    "rep": 16
  },
  {
    "alpha_hill": 1.650295502865648,
    "xi": 0.5271009014780186,
    "W1": 0.07490396033102165,
    "n_lifetimes": 486,
    "family": "levy_alpha_2.0",
    "rep": 17
  },
  {
    "alpha_hill": 1.6263573343592068,
    "xi": 0.4756350132318069,
    "W1": 0.033527314210587314,
    "n_lifetimes": 508,
    "family": "levy_alpha_2.0",
    "rep": 18
  },
  {
    "alpha_hill": 1.5577586389299658,
    "xi": 0.5093764406119625,
    "W1": 0.013445038174215558,
    "n_lifetimes": 504,
    "family": "levy_alpha_2.0",
    "rep": 19
  },
  {
    "alpha_hill": 1.7239844711279586,
    "xi": 0.4552248102122317,
    "W1": 0.034653389141441907,
    "n_lifetimes": 509,
    "family": "levy_alpha_2.0",
    "rep": 20
  },
  {
    "alpha_hill": 1.629076330815162,
    "xi": 0.48621059400575073,
    "W1": 0.06683105811812569,
    "n_lifetimes": 514,
    "family": "levy_alpha_2.0",
    "rep": 21
  },
  {
    "alpha_hill": 1.6032868777867717,
    "xi": 0.5225471296953433,
    "W1": 0.009383976132668897,
    "n_lifetimes": 494,
    "family": "levy_alpha_2.0",
    "rep": 22
  },
  {
    "alpha_hill": 2.1185832203205726,
    "xi": 0.29454526095642375,
    "W1": 0.03193205193820168,
    "n_lifetimes": 498,
    "family": "levy_alpha_2.0",
    "rep": 23
  },
  {
    "alpha_hill": 1.6457905614303912,
    "xi": 0.5929560368776128,
    "W1": 0.03271786520603687,
    "n_lifetimes": 513,
    "family": "levy_alpha_2.0",
    "rep": 24
  },
  {
    "alpha_hill": 1.7269169071428099,
    "xi": 0.43294177022672853,
    "W1": 0.027840773768609193,
    "n_lifetimes": 510,
    "family": "levy_alpha_2.0",
    "rep": 25
  },
  {
    "alpha_hill": 1.4797010508566166,
    "xi": 0.4661573240207277,
    "W1": 0.1734643223149011,
    "n_lifetimes": 490,
    "family": "levy_alpha_2.0",
    "rep": 26
  },
  {
    "alpha_hill": 1.5626611019184067,
    "xi": 0.5902179706666955,
    "W1": 0.03715066175559925,
    "n_lifetimes": 521,
    "family": "levy_alpha_2.0",
    "rep": 27
  },
  {
    "alpha_hill": 1.6974267968111934,
    "xi": 0.43411103821071295,
    "W1": 0.02673128385252426,
    "n_lifetimes": 501,
    "family": "levy_alpha_2.0",
    "rep": 28
  },
  {
    "alpha_hill": 2.1091958019689487,
    "xi": 0.36286842069440584,
    "W1": 0.013143168536416071,
    "n_lifetimes": 483,
    "family": "levy_alpha_2.0",
    "rep": 29
  },
  {
    "alpha_hill": 1.663073374869228,
    "xi": 0.2986173487691808,
    "W1": 0.06070482931452092,
    "n_lifetimes": 498,
    "family": "levy_alpha_2.0",
    "rep": 30
  },
  {
    "alpha_hill": 1.6792014487085658,
    "xi": 0.4201512620814276,
    "W1": 0.024228139912181316,
    "n_lifetimes": 492,
    "family": "levy_alpha_2.0",
    "rep": 31
  },
  {
    "alpha_hill": 1.4909494948036908,
    "xi": 0.5567637985000278,
    "W1": 0.027293836293545835,
    "n_lifetimes": 513,
    "family": "levy_alpha_2.0",
    "rep": 32
  },
  {
    "alpha_hill": 1.5085795826177424,
    "xi": 0.3993915704876406,
    "W1": 0.013630800220307129,
    "n_lifetimes": 490,
    "family": "levy_alpha_2.0",
    "rep": 33
  },
  {
    "alpha_hill": 1.5726742001969383,
    "xi": 0.5203185645329373,
    "W1": 0.06385310086529905,
    "n_lifetimes": 497,
    "family": "levy_alpha_2.0",
    "rep": 34
  },
  {
    "alpha_hill": 1.6069010149670242,
    "xi": 0.49853179732502356,
    "W1": 0.05415610125080479,
    "n_lifetimes": 503,
    "family": "levy_alpha_2.0",
    "rep": 35
  },
  {
    "alpha_hill": 1.899262535498181,
    "xi": 0.3168855359678724,
    "W1": 0.06278551280867443,
    "n_lifetimes": 500,
    "family": "levy_alpha_2.0",
    "rep": 36
  },
  {
    "alpha_hill": 1.8823715025477934,
    "xi": 0.34289884627567657,
    "W1": 0.010662074395868854,
    "n_lifetimes": 493,
    "family": "levy_alpha_2.0",
    "rep": 37
  },
  {
    "alpha_hill": 1.629148512448011,
    "xi": 0.35172346170593166,
    "W1": 0.0218766560482819,
    "n_lifetimes": 498,
    "family": "levy_alpha_2.0",
    "rep": 38
  },
  {
    "alpha_hill": 1.7644979621882853,
    "xi": 0.4830122865358105,
    "W1": 0.0418386603699268,
    "n_lifetimes": 514,
    "family": "levy_alpha_2.0",
    "rep": 39
  },
  {
    "alpha_hill": 1.7190917069876996,
    "xi": 0.4724585326730397,
    "W1": 0.04328922883006435,
    "n_lifetimes": 487,
    "family": "levy_alpha_2.0",
    "rep": 40
  },
  {
    "alpha_hill": 1.7145126516545788,
    "xi": 0.5246185388706724,
    "W1": 0.04372817180137345,
    "n_lifetimes": 498,
    "family": "levy_alpha_2.0",
    "rep": 41
  },
  {
    "alpha_hill": 1.9077461686071417,
    "xi": 0.3136038858342042,
    "W1": 0.03827472786706963,
    "n_lifetimes": 512,
    "family": "levy_alpha_2.0",
    "rep": 42
  },
  {
    "alpha_hill": 1.692447854753276,
    "xi": 0.2952329733810231,
    "W1": 0.036095545350731,
    "n_lifetimes": 508,
    "family": "levy_alpha_2.0",
    "rep": 43
  },
  {
    "alpha_hill": 1.6849971409948465,
    "xi": 0.48096365230683885,
    "W1": 0.014597069476312358,
    "n_lifetimes": 500,
    "family": "levy_alpha_2.0",
    "rep": 44
  },
  {
    "alpha_hill": 1.8227589111761577,
    "xi": 0.3844781755994574,
    "W1": 0.036890911719440825,
    "n_lifetimes": 501,
    "family": "levy_alpha_2.0",
    "rep": 45
  },
  {
    "alpha_hill": 1.6204854652989222,
    "xi": 0.5361438012860434,
    "W1": 0.04178860120862941,
    "n_lifetimes": 487,
    "family": "levy_alpha_2.0",
    "rep": 46
  },
  {
    "alpha_hill": 1.6281808222675505,
    "xi": 0.5049116721405614,
    "W1": 0.030324671141626514,
    "n_lifetimes": 497,
    "family": "levy_alpha_2.0",
    "rep": 47
  },
  {
    "alpha_hill": 1.7393056788900423,
    "xi": 0.5202550013391918,
    "W1": 0.008866596198214149,
    "n_lifetimes": 475,
    "family": "levy_alpha_2.0",
    "rep": 48
  },
  {
    "alpha_hill": 1.8313431276286491,
    "xi": 0.5125834986674346,
    "W1": 0.01091225638986949,
    "n_lifetimes": 491,
    "family": "levy_alpha_2.0",
    "rep": 49
  },
  {
    "alpha_hill": 1.9521870444713862,
    "xi": 0.2082509369568363,
    "W1": 0.04017276634825892,
    "n_lifetimes": 498,
    "family": "brownian_sigma_1.0",
    "rep": 0
  },
  {
    "alpha_hill": 1.4835003144902084,
    "xi": 0.5466047345606043,
    "W1": 0.008193314952757755,
    "n_lifetimes": 502,
    "family": "brownian_sigma_1.0",
    "rep": 1
  },
  {
    "alpha_hill": 1.662446232422499,
    "xi": 0.4348567799225705,
    "W1": 0.020427311498837232,
    "n_lifetimes": 489,
    "family": "brownian_sigma_1.0",
    "rep": 2
  },
  {
    "alpha_hill": 1.5262601305825827,
    "xi": 0.6053227096776925,
    "W1": 0.02937761576599757,
    "n_lifetimes": 510,
    "family": "brownian_sigma_1.0",
    "rep": 3
  },
  {
    "alpha_hill": 1.3737529675085316,
    "xi": 0.6334088395284183,
    "W1": 0.021252493693729668,
    "n_lifetimes": 511,
    "family": "brownian_sigma_1.0",
    "rep": 4
  },
  {
    "alpha_hill": 2.070879632112487,
    "xi": 0.33766424263686534,
    "W1": 0.018488412228987988,
    "n_lifetimes": 490,
    "family": "brownian_sigma_1.0",
    "rep": 5
  },
  {
    "alpha_hill": 1.660772714272671,
    "xi": 0.440082022061577,
    "W1": 0.03525521097681917,
    "n_lifetimes": 514,
    "family": "brownian_sigma_1.0",
    "rep": 6
  },
  {
    "alpha_hill": 1.769236605080702,
    "xi": 0.5619224823898539,
    "W1": 0.009783140318713291,
    "n_lifetimes": 506,
    "family": "brownian_sigma_1.0",
    "rep": 7
  },
  {
    "alpha_hill": 1.7662645281195972,
    "xi": 0.4943669480271624,
    "W1": 0.06311860323525818,
    "n_lifetimes": 510,
    "family": "brownian_sigma_1.0",
    "rep": 8
  },
  {
    "alpha_hill": 1.9245825395432667,
    "xi": 0.2987179621464069,
    "W1": 0.03273554429950179,
    "n_lifetimes": 497,
    "family": "brownian_sigma_1.0",
    "rep": 9
  },
  {
    "alpha_hill": 1.5667055143742425,
    "xi": 0.5219424977710885,
    "W1": 0.01589507432645823,
    "n_lifetimes": 517,
    "family": "brownian_sigma_1.0",
    "rep": 10
  },
  {
    "alpha_hill": 1.5092679134866758,
    "xi": 0.47356553628589265,
    "W1": 0.015537759288374794,
    "n_lifetimes": 485,
    "family": "brownian_sigma_1.0",
    "rep": 11
  },
  {
    "alpha_hill": 1.6196255583160717,
    "xi": 0.39487115048234667,
    "W1": 0.08660232633599725,
    "n_lifetimes": 507,
    "family": "brownian_sigma_1.0",
    "rep": 12
  },
  {
    "alpha_hill": 1.649070559665109,
    "xi": 0.4128293306839811,
    "W1": 0.03918362883454629,
    "n_lifetimes": 469,
    "family": "brownian_sigma_1.0",
    "rep": 13
  },
  {
    "alpha_hill": 1.8182170510803917,
    "xi": 0.5139639640206611,
    "W1": 0.017751599389472315,
    "n_lifetimes": 494,
    "family": "brownian_sigma_1.0",
    "rep": 14
  },
  {
    "alpha_hill": 1.6495333670582555,
    "xi": 0.4875185798611658,
    "W1": 0.008478173168804615,
    "n_lifetimes": 493,
    "family": "brownian_sigma_1.0",
    "rep": 15
  },
  {
    "alpha_hill": 1.456535152704175,
    "xi": 0.5633859240923342,
    "W1": 0.016932329707884067,
    "n_lifetimes": 503,
    "family": "brownian_sigma_1.0",
    "rep": 16
  },
  {
    "alpha_hill": 1.4627775048640268,
    "xi": 0.7965737146567329,
    "W1": 0.021619058590630912,
    "n_lifetimes": 504,
    "family": "brownian_sigma_1.0",
    "rep": 17
  },
  {
    "alpha_hill": 1.8120149924144506,
    "xi": 0.5851039939905593,
    "W1": 0.010622781725221922,
    "n_lifetimes": 510,
    "family": "brownian_sigma_1.0",
    "rep": 18
  },
  {
    "alpha_hill": 1.8700828522097963,
    "xi": 0.3271146894802959,
    "W1": 0.03505084540455772,
    "n_lifetimes": 506,
    "family": "brownian_sigma_1.0",
    "rep": 19
  },
  {
    "alpha_hill": 1.7548012391480767,
    "xi": 0.40891141852993296,
    "W1": 0.02774645563706342,
    "n_lifetimes": 509,
    "family": "brownian_sigma_1.0",
    "rep": 20
  },
  {
    "alpha_hill": 1.500104794847995,
    "xi": 0.7192533838222515,
    "W1": 0.024054739745030435,
    "n_lifetimes": 489,
    "family": "brownian_sigma_1.0",
    "rep": 21
  },
  {
    "alpha_hill": 1.6248409620733546,
    "xi": 0.520611490796948,
    "W1": 0.021307809830721607,
    "n_lifetimes": 478,
    "family": "brownian_sigma_1.0",
    "rep": 22
  },
  {
    "alpha_hill": 1.752200162183656,
    "xi": 0.43494731781876306,
    "W1": 0.022525381112688356,
    "n_lifetimes": 515,
    "family": "brownian_sigma_1.0",
    "rep": 23
  },
  {
    "alpha_hill": 1.5382050809733667,
    "xi": 0.48898998253015835,
    "W1": 0.01977972077014082,
    "n_lifetimes": 476,
    "family": "brownian_sigma_1.0",
    "rep": 24
  },
  {
    "alpha_hill": 1.6680097025695806,
    "xi": 0.46159049281228404,
    "W1": 0.019190359232605116,
    "n_lifetimes": 487,
    "family": "brownian_sigma_1.0",
    "rep": 25
  },
  {
    "alpha_hill": 1.5778297754287096,
    "xi": 0.29754937871842996,
    "W1": 0.02916012440366146,
    "n_lifetimes": 496,
    "family": "brownian_sigma_1.0",
    "rep": 26
  },
  {
    "alpha_hill": 1.8108033431177515,
    "xi": 0.28024485555539,
    "W1": 0.012249577965247529,
    "n_lifetimes": 508,
    "family": "brownian_sigma_1.0",
    "rep": 27
  },
  {
    "alpha_hill": 1.6935196387977778,
    "xi": 0.4426704420974527,
    "W1": 0.008572283453125608,
    "n_lifetimes": 485,
    "family": "brownian_sigma_1.0",
    "rep": 28
  },
  {
    "alpha_hill": 1.74654689483877,
    "xi": 0.4049946822712497,
    "W1": 0.07851008607853256,
    "n_lifetimes": 492,
    "family": "brownian_sigma_1.0",
    "rep": 29
  },
  {
    "alpha_hill": 1.631151759083547,
    "xi": 0.5787999356500219,
    "W1": 0.01374687519038362,
    "n_lifetimes": 507,
    "family": "brownian_sigma_1.0",
    "rep": 30
  },
  {
    "alpha_hill": 1.8444190075886646,
    "xi": 0.3190285702407135,
    "W1": 0.009407252064414695,
    "n_lifetimes": 498,
    "family": "brownian_sigma_1.0",
    "rep": 31
  },
  {
    "alpha_hill": 1.7569217271323092,
    "xi": 0.2800890365634005,
    "W1": 0.12007987430211299,
    "n_lifetimes": 486,
    "family": "brownian_sigma_1.0",
    "rep": 32
  },
  {
    "alpha_hill": 1.6119639544892475,
    "xi": 0.5204233777041724,
    "W1": 0.05822622898641538,
    "n_lifetimes": 518,
    "family": "brownian_sigma_1.0",
    "rep": 33
  },
  {
    "alpha_hill": 1.6685996145293707,
    "xi": 0.4239122011213987,
    "W1": 0.016023705416195102,
    "n_lifetimes": 514,
    "family": "brownian_sigma_1.0",
    "rep": 34
  },
  {
    "alpha_hill": 1.681838510645718,
    "xi": 0.4898318860750793,
    "W1": 0.015578051291273213,
    "n_lifetimes": 507,
    "family": "brownian_sigma_1.0",
    "rep": 35
  },
  {
    "alpha_hill": 1.9785370476609836,
    "xi": 0.29798689898633657,
    "W1": 0.050754223851716754,
    "n_lifetimes": 506,
    "family": "brownian_sigma_1.0",
    "rep": 36
  },
  {
    "alpha_hill": 1.662791736360063,
    "xi": 0.3731205657947536,
    "W1": 0.018799592611628703,
    "n_lifetimes": 506,
    "family": "brownian_sigma_1.0",
    "rep": 37
  },
  {
    "alpha_hill": 1.8031681368600057,
    "xi": 0.38962609378594915,
    "W1": 0.046038068962815204,
    "n_lifetimes": 492,
    "family": "brownian_sigma_1.0",
    "rep": 38
  },
  {
    "alpha_hill": 1.6052373528994826,
    "xi": 0.47527279696171176,
    "W1": 0.012015201910592898,
    "n_lifetimes": 499,
    "family": "brownian_sigma_1.0",
    "rep": 39
  },
  {
    "alpha_hill": 1.6720284328298622,
    "xi": 0.49596203291442736,
    "W1": 0.015977996615662945,
    "n_lifetimes": 507,
    "family": "brownian_sigma_1.0",
    "rep": 40
  },
  {
    "alpha_hill": 1.6513169164763217,
    "xi": 0.38565862287252695,
    "W1": 0.011189083932056615,
    "n_lifetimes": 512,
    "family": "brownian_sigma_1.0",
    "rep": 41
  },
  {
    "alpha_hill": 1.4907968087469645,
    "xi": 0.5990773662349964,
    "W1": 0.020668148250171,
    "n_lifetimes": 497,
    "family": "brownian_sigma_1.0",
    "rep": 42
  },
  {
    "alpha_hill": 1.7314061705944455,
    "xi": 0.521343443799923,
    "W1": 0.02464991339704016,
    "n_lifetimes": 505,
    "family": "brownian_sigma_1.0",
    "rep": 43
  },
  {
    "alpha_hill": 1.532111477839367,
    "xi": 0.5589339880701558,
    "W1": 0.03286867046516505,
    "n_lifetimes": 507,
    "family": "brownian_sigma_1.0",
    "rep": 44
  },
  {
    "alpha_hill": 1.783699749069658,
    "xi": 0.37157747743685254,
    "W1": 0.05697145605919328,
    "n_lifetimes": 492,
    "family": "brownian_sigma_1.0",
    "rep": 45
  },
  {
    "alpha_hill": 1.42891122655006,
    "xi": 0.5340282870978232,
    "W1": 0.043883866113908064,
    "n_lifetimes": 486,
    "family": "brownian_sigma_1.0",
    "rep": 46
  },
  {
    "alpha_hill": 1.5747756977802683,
    "xi": 0.5274325310493724,
    "W1": 0.03946234843180195,
    "n_lifetimes": 505,
    "family": "brownian_sigma_1.0",
    "rep": 47
  },
  {
    "alpha_hill": 1.7232997566828647,
    "xi": 0.2891266261055387,
    "W1": 0.039612585191208874,
    "n_lifetimes": 477,
    "family": "brownian_sigma_1.0",
    "rep": 48
  },
  {
    "alpha_hill": 1.7677169844200786,
    "xi": 0.3733999117622129,
    "W1": 0.008958690758814421,
    "n_lifetimes": 491,
    "family": "brownian_sigma_1.0",
    "rep": 49
  },
  {
    "alpha_hill": 1.8087211278920337,
    "xi": 0.2902849204744095,
    "W1": 0.019307975738440536,
    "n_lifetimes": 462,
    "family": "restricted_w_0.5",
    "rep": 0
  },
  {
    "alpha_hill": 1.6042037758393517,
    "xi": 0.5409484034858781,
    "W1": 0.07142862059323428,
    "n_lifetimes": 506,
    "family": "restricted_w_0.5",
    "rep": 1
  },
  {
    "alpha_hill": 1.91483942606669,
    "xi": 0.42944497018176203,
    "W1": 0.024223843171671252,
    "n_lifetimes": 496,
    "family": "restricted_w_0.5",
    "rep": 2
  },
  {
    "alpha_hill": 1.9462334787075988,
    "xi": 0.3285627955258342,
    "W1": 0.014504846921291118,
    "n_lifetimes": 500,
    "family": "restricted_w_0.5",
    "rep": 3
  },
  {
    "alpha_hill": 1.8839475577841343,
    "xi": 0.4548630512734427,
    "W1": 0.07904663570209426,
    "n_lifetimes": 478,
    "family": "restricted_w_0.5",
    "rep": 4
  },
  {
    "alpha_hill": 1.5095145971613386,
    "xi": 0.5024317255526008,
    "W1": 0.04661961032279313,
    "n_lifetimes": 495,
    "family": "restricted_w_0.5",
    "rep": 5
  },
  {
    "alpha_hill": 1.6209940221946044,
    "xi": 0.44513609347519933,
    "W1": 0.038513361269226054,
    "n_lifetimes": 516,
    "family": "restricted_w_0.5",
    "rep": 6
  },
  {
    "alpha_hill": 1.6590518402902528,
    "xi": 0.5927240539724374,
    "W1": 0.023985999544015493,
    "n_lifetimes": 510,
    "family": "restricted_w_0.5",
    "rep": 7
  },
  {
    "alpha_hill": 1.6262095206161329,
    "xi": 0.44552436520098193,
    "W1": 0.023949363186651543,
    "n_lifetimes": 498,
    "family": "restricted_w_0.5",
    "rep": 8
  },
  {
    "alpha_hill": 1.6219572377528688,
    "xi": 0.4394063675389088,
    "W1": 0.014129222159097128,
    "n_lifetimes": 512,
    "family": "restricted_w_0.5",
    "rep": 9
  },
  {
    "alpha_hill": 1.81447820038975,
    "xi": 0.3040821974045099,
    "W1": 0.020184798620016098,
    "n_lifetimes": 494,
    "family": "restricted_w_0.5",
    "rep": 10
  },
  {
    "alpha_hill": 1.6889538214540019,
    "xi": 0.25314261782080694,
    "W1": 0.057626233544552985,
    "n_lifetimes": 510,
    "family": "restricted_w_0.5",
    "rep": 11
  },
  {
    "alpha_hill": 1.637749639930939,
    "xi": 0.6556923593104559,
    "W1": 0.023557686885177804,
    "n_lifetimes": 503,
    "family": "restricted_w_0.5",
    "rep": 12
  },
  {
    "alpha_hill": 2.013416278638369,
    "xi": 0.48761856308601936,
    "W1": 0.016807603404539677,
    "n_lifetimes": 504,
    "family": "restricted_w_0.5",
    "rep": 13
  },
  {
    "alpha_hill": 1.6842809692356793,
    "xi": 0.5077656845163763,
    "W1": 0.033774279658352745,
    "n_lifetimes": 517,
    "family": "restricted_w_0.5",
    "rep": 14
  },
  {
    "alpha_hill": 1.668445664729052,
    "xi": 0.4084988350089649,
    "W1": 0.03573837291971392,
    "n_lifetimes": 496,
    "family": "restricted_w_0.5",
    "rep": 15
  },
  {
    "alpha_hill": 1.5671769414738388,
    "xi": 0.5191444005930509,
    "W1": 0.013320587105487662,
    "n_lifetimes": 502,
    "family": "restricted_w_0.5",
    "rep": 16
  },
  {
    "alpha_hill": 1.6563191914146203,
    "xi": 0.36333618473578844,
    "W1": 0.06021463812565685,
    "n_lifetimes": 478,
    "family": "restricted_w_0.5",
    "rep": 17
  },
  {
    "alpha_hill": 1.7458123824198006,
    "xi": 0.4013843988386906,
    "W1": 0.043002466279183624,
    "n_lifetimes": 504,
    "family": "restricted_w_0.5",
    "rep": 18
  },
  {
    "alpha_hill": 1.6637499252262642,
    "xi": 0.5967380404255469,
    "W1": 0.05741653712853591,
    "n_lifetimes": 490,
    "family": "restricted_w_0.5",
    "rep": 19
  },
  {
    "alpha_hill": 1.589805636196847,
    "xi": 0.3805042362318068,
    "W1": 0.03093014953754672,
    "n_lifetimes": 497,
    "family": "restricted_w_0.5",
    "rep": 20
  },
  {
    "alpha_hill": 1.7709340034196297,
    "xi": 0.33776629363956184,
    "W1": 0.032633314167089096,
    "n_lifetimes": 498,
    "family": "restricted_w_0.5",
    "rep": 21
  },
  {
    "alpha_hill": 1.6326232056866394,
    "xi": 0.5762075242945424,
    "W1": 0.029627821837756137,
    "n_lifetimes": 518,
    "family": "restricted_w_0.5",
    "rep": 22
  },
  {
    "alpha_hill": 1.582680336336318,
    "xi": 0.5039803091661053,
    "W1": 0.04462033704097844,
    "n_lifetimes": 498,
    "family": "restricted_w_0.5",
    "rep": 23
  },
  {
    "alpha_hill": 1.9692847968168041,
    "xi": 0.20788908470559658,
    "W1": 0.03565973659104159,
    "n_lifetimes": 516,
    "family": "restricted_w_0.5",
    "rep": 24
  },
  {
    "alpha_hill": 1.6288312448395037,
    "xi": 0.4344388254436326,
    "W1": 0.0163165036032644,
    "n_lifetimes": 515,
    "family": "restricted_w_0.5",
    "rep": 25
  },
  {
    "alpha_hill": 1.64355066199734,
    "xi": 0.5808811426870375,
    "W1": 0.027776996387669426,
    "n_lifetimes": 498,
    "family": "restricted_w_0.5",
    "rep": 26
  },
  {
    "alpha_hill": 1.7606699203242877,
    "xi": 0.4573057505304921,
    "W1": 0.05676782289603381,
    "n_lifetimes": 498,
    "family": "restricted_w_0.5",
    "rep": 27
  },
  {
    "alpha_hill": 1.8976028309631214,
    "xi": 0.33659920711137353,
    "W1": 0.054774188186508935,
    "n_lifetimes": 504,
    "family": "restricted_w_0.5",
    "rep": 28
  },
  {
    "alpha_hill": 1.6540175633391299,
    "xi": 0.5054936238588177,
    "W1": 0.02959726076725895,
    "n_lifetimes": 483,
    "family": "restricted_w_0.5",
    "rep": 29
  },
  {
    "alpha_hill": 1.7655046185429233,
    "xi": 0.41687362190610877,
    "W1": 0.13817896163244459,
    "n_lifetimes": 511,
    "family": "restricted_w_0.5",
    "rep": 30
  },
  {
    "alpha_hill": 1.8737861104487636,
    "xi": 0.3903182057597816,
    "W1": 0.020458238218144704,
    "n_lifetimes": 483,
    "family": "restricted_w_0.5",
    "rep": 31
  },
  {
    "alpha_hill": 1.6392176312667117,
    "xi": 0.34062350442600337,
    "W1": 0.02743205398392538,
    "n_lifetimes": 520,
    "family": "restricted_w_0.5",
    "rep": 32
  },
  {
    "alpha_hill": 1.79554091457929,
    "xi": 0.44677707158416735,
    "W1": 0.04554656101903538,
    "n_lifetimes": 496,
    "family": "restricted_w_0.5",
    "rep": 33
  },
  {
    "alpha_hill": 1.6088553189374355,
    "xi": 0.4586696610786648,
    "W1": 0.083346865326199,
    "n_lifetimes": 511,
    "family": "restricted_w_0.5",
    "rep": 34
  },
  {
    "alpha_hill": 1.543686534291198,
    "xi": 0.5508352368658069,
    "W1": 0.05033889708337971,
    "n_lifetimes": 495,
    "family": "restricted_w_0.5",
    "rep": 35
  },
  {
    "alpha_hill": 1.7633246165126801,
    "xi": 0.37491413061749984,
    "W1": 0.04834861089997364,
    "n_lifetimes": 505,
    "family": "restricted_w_0.5",
    "rep": 36
  },
  {
    "alpha_hill": 1.8168030668560697,
    "xi": 0.2838113056113871,
    "W1": 0.07101988363114485,
    "n_lifetimes": 473,
    "family": "restricted_w_0.5",
    "rep": 37
  },
  {
    "alpha_hill": 1.4684988549889786,
    "xi": 0.589145744364056,
    "W1": 0.04456256436397056,
    "n_lifetimes": 504,
    "family": "restricted_w_0.5",
    "rep": 38
  },
  {
    "alpha_hill": 1.7575049884122087,
    "xi": 0.47340582768346445,
    "W1": 0.022550768423938192,
    "n_lifetimes": 492,
    "family": "restricted_w_0.5",
    "rep": 39
  },
  {
    "alpha_hill": 1.7241189818254437,
    "xi": 0.41344141234125253,
    "W1": 0.05281823721747004,
    "n_lifetimes": 480,
    "family": "restricted_w_0.5",
    "rep": 40
  },
  {
    "alpha_hill": 1.9196320961671929,
    "xi": 0.1681190432691212,
    "W1": 0.033856657794552034,
    "n_lifetimes": 512,
    "family": "restricted_w_0.5",
    "rep": 41
  },
  {
    "alpha_hill": 1.6361649727584622,
    "xi": 0.5057054130929133,
    "W1": 0.02038282299170046,
    "n_lifetimes": 494,
    "family": "restricted_w_0.5",
    "rep": 42
  },
  {
    "alpha_hill": 1.6596945546650141,
    "xi": 0.4667975192888686,
    "W1": 0.03366361863333556,
    "n_lifetimes": 482,
    "family": "restricted_w_0.5",
    "rep": 43
  },
  {
    "alpha_hill": 1.9287254184407006,
    "xi": 0.45488981103081877,
    "W1": 0.02858311118637399,
    "n_lifetimes": 500,
    "family": "restricted_w_0.5",
    "rep": 44
  },
  {
    "alpha_hill": 1.5654841268548612,
    "xi": 0.46790517644995666,
    "W1": 0.11251053437099898,
    "n_lifetimes": 492,
    "family": "restricted_w_0.5",
    "rep": 45
  },
  {
    "alpha_hill": 2.001981834377551,
    "xi": 0.33412631760520306,
    "W1": 0.022586845541258508,
    "n_lifetimes": 493,
    "family": "restricted_w_0.5",
    "rep": 46
  },
  {
    "alpha_hill": 1.6640439790504211,
    "xi": 0.4904390772311236,
    "W1": 0.018192242374598308,
    "n_lifetimes": 498,
    "family": "restricted_w_0.5",
    "rep": 47
  },
  {
    "alpha_hill": 1.5179936670087648,
    "xi": 0.4948877145123678,
    "W1": 0.063401962032091,
    "n_lifetimes": 480,
    "family": "restricted_w_0.5",
    "rep": 48
  },
  {
    "alpha_hill": 1.8005723811198224,
    "xi": 0.3206351102841527,
    "W1": 0.026041562956454024,
    "n_lifetimes": 496,
    "family": "restricted_w_0.5",
    "rep": 49
  },
  {
    "alpha_hill": 1.901169220546186,
    "xi": 0.31449462834716374,
    "W1": 0.04269780036985041,
    "n_lifetimes": 475,
    "family": "restricted_w_1.0",
    "rep": 0
  },
  {
    "alpha_hill": 1.7522597508145326,
    "xi": 0.4518041653243778,
    "W1": 0.053597947954061365,
    "n_lifetimes": 488,
    "family": "restricted_w_1.0",
    "rep": 1
  },
  {
    "alpha_hill": 1.636034240443336,
    "xi": 0.46305282126880176,
    "W1": 0.019605830722671296,
    "n_lifetimes": 494,
    "family": "restricted_w_1.0",
    "rep": 2
  },
  {
    "alpha_hill": 1.6103358971797113,
    "xi": 0.5932012289280575,
    "W1": 0.02880199671624732,
    "n_lifetimes": 497,
    "family": "restricted_w_1.0",
    "rep": 3
  },
  {
    "alpha_hill": 1.6647730646903913,
    "xi": 0.5375431944445537,
    "W1": 0.09449187338405513,
    "n_lifetimes": 517,
    "family": "restricted_w_1.0",
    "rep": 4
  },
  {
    "alpha_hill": 1.862491374700709,
    "xi": 0.34958797075960146,
    "W1": 0.1001752820504755,
    "n_lifetimes": 497,
    "family": "restricted_w_1.0",
    "rep": 5
  },
  {
    "alpha_hill": 1.8737144333688862,
    "xi": 0.2784141044391016,
    "W1": 0.1732006640072151,
    "n_lifetimes": 502,
    "family": "restricted_w_1.0",
    "rep": 6
  },
  {
    "alpha_hill": 1.6202470907691424,
    "xi": 0.4322488146674735,
    "W1": 0.12589353613740345,
    "n_lifetimes": 511,
    "family": "restricted_w_1.0",
    "rep": 7
  },
  {
    "alpha_hill": 1.4660652520396251,
    "xi": 0.6166866320681987,
    "W1": 0.01572001772388569,
    "n_lifetimes": 501,
    "family": "restricted_w_1.0",
    "rep": 8
  },
  {
    "alpha_hill": 1.8525574864181058,
    "xi": 0.4935920391907258,
    "W1": 0.02470450546794258,
    "n_lifetimes": 506,
    "family": "restricted_w_1.0",
    "rep": 9
  },
  {
    "alpha_hill": 1.4956146547018172,
    "xi": 0.6197243283743636,
    "W1": 0.06284585252403094,
    "n_lifetimes": 490,
    "family": "restricted_w_1.0",
    "rep": 10
  },
  {
    "alpha_hill": 1.768164891472055,
    "xi": 0.35663013116832,
    "W1": 0.024392184406738984,
    "n_lifetimes": 501,
    "family": "restricted_w_1.0",
    "rep": 11
  },
  {
    "alpha_hill": 1.953096686142892,
    "xi": 0.1504645221611306,
    "W1": 0.02458340431897541,
    "n_lifetimes": 490,
    "family": "restricted_w_1.0",
    "rep": 12
  },
  {
    "alpha_hill": 1.8144384764060437,
    "xi": 0.318193853130297,
    "W1": 0.017263407272081453,
    "n_lifetimes": 502,
    "family": "restricted_w_1.0",
    "rep": 13
  },
  {
    "alpha_hill": 1.7244945621059333,
    "xi": 0.3840749263821617,
    "W1": 0.06067123558025815,
    "n_lifetimes": 501,
    "family": "restricted_w_1.0",
    "rep": 14
  },
  {
    "alpha_hill": 1.6849755795562453,
    "xi": 0.4632330346892172,
    "W1": 0.0353790437876853,
    "n_lifetimes": 501,
    "family": "restricted_w_1.0",
    "rep": 15
  },
  {
    "alpha_hill": 1.8338287227394594,
    "xi": 0.3817618458338966,
    "W1": 0.0329636018539691,
    "n_lifetimes": 496,
    "family": "restricted_w_1.0",
    "rep": 16
  },
  {
    "alpha_hill": 1.780248329768286,
    "xi": 0.42232061047453273,
    "W1": 0.04623803585377391,
    "n_lifetimes": 493,
    "family": "restricted_w_1.0",
    "rep": 17
  },
  {
    "alpha_hill": 1.4776232317898665,
    "xi": 0.4654473348210888,
    "W1": 0.015761745502721268,
    "n_lifetimes": 514,
    "family": "restricted_w_1.0",
    "rep": 18
  },
  {
    "alpha_hill": 1.7170784416229432,
    "xi": 0.4232626253638434,
    "W1": 0.0795903291309927,
    "n_lifetimes": 487,
    "family": "restricted_w_1.0",
    "rep": 19
  },
  {
    "alpha_hill": 1.5776137733340116,
    "xi": 0.5434876716183805,
    "W1": 0.031110034696113564,
    "n_lifetimes": 522,
    "family": "restricted_w_1.0",
    "rep": 20
  },
  {
    "alpha_hill": 1.650252672834713,
    "xi": 0.46202207613463997,
    "W1": 0.040719585477634046,
    "n_lifetimes": 492,
    "family": "restricted_w_1.0",
    "rep": 21
  },
  {
    "alpha_hill": 1.8026694004624684,
    "xi": 0.40784036919703603,
    "W1": 0.028074114316534053,
    "n_lifetimes": 492,
    "family": "restricted_w_1.0",
    "rep": 22
  },
  {
    "alpha_hill": 1.8697106318716437,
    "xi": 0.26230609669337146,
    "W1": 0.04333799701722449,
    "n_lifetimes": 483,
    "family": "restricted_w_1.0",
    "rep": 23
  },
  {
    "alpha_hill": 1.948051019522609,
    "xi": 0.3208098234550543,
    "W1": 0.043240857631295954,
    "n_lifetimes": 494,
    "family": "restricted_w_1.0",
    "rep": 24
  },
  {
    "alpha_hill": 1.7884942316288914,
    "xi": 0.3623895958360644,
    "W1": 0.05172039301757769,
    "n_lifetimes": 479,
    "family": "restricted_w_1.0",
    "rep": 25
  },
  {
    "alpha_hill": 1.6044914091730749,
    "xi": 0.3783329986082645,
    "W1": 0.01882691847294255,
    "n_lifetimes": 495,
    "family": "restricted_w_1.0",
    "rep": 26
  },
  {
    "alpha_hill": 1.8345538184229377,
    "xi": 0.4491696794819943,
    "W1": 0.014748023507249516,
    "n_lifetimes": 485,
    "family": "restricted_w_1.0",
    "rep": 27
  },
  {
    "alpha_hill": 1.5804681356337407,
    "xi": 0.4872898129639436,
    "W1": 0.09734180862776004,
    "n_lifetimes": 493,
    "family": "restricted_w_1.0",
    "rep": 28
  },
  {
    "alpha_hill": 1.6460784778115647,
    "xi": 0.5517156498360807,
    "W1": 0.031148382887970158,
    "n_lifetimes": 504,
    "family": "restricted_w_1.0",
    "rep": 29
  },
  {
    "alpha_hill": 1.7323823531069842,
    "xi": 0.4871809899584868,
    "W1": 0.07075251833737556,
    "n_lifetimes": 505,
    "family": "restricted_w_1.0",
    "rep": 30
  },
  {
    "alpha_hill": 1.5783681439855328,
    "xi": 0.5398378110706785,
    "W1": 0.061701590347779375,
    "n_lifetimes": 497,
    "family": "restricted_w_1.0",
    "rep": 31
  },
  {
    "alpha_hill": 1.516586932600758,
    "xi": 0.5789701832980516,
    "W1": 0.016058189463549023,
    "n_lifetimes": 481,
    "family": "restricted_w_1.0",
    "rep": 32
  },
  {
    "alpha_hill": 1.7398068476648558,
    "xi": 0.34190897196749404,
    "W1": 0.04552158696079914,
    "n_lifetimes": 510,
    "family": "restricted_w_1.0",
    "rep": 33
  },
  {
    "alpha_hill": 1.9828722396095684,
    "xi": 0.2901215672495121,
    "W1": 0.02443696718485361,
    "n_lifetimes": 499,
    "family": "restricted_w_1.0",
    "rep": 34
  },
  {
    "alpha_hill": 1.68728100409863,
    "xi": 0.4979069191915684,
    "W1": 0.040293674766092295,
    "n_lifetimes": 476,
    "family": "restricted_w_1.0",
    "rep": 35
  },
  {
    "alpha_hill": 1.4891520610764244,
    "xi": 0.5656632159676052,
    "W1": 0.033608940602552304,
    "n_lifetimes": 511,
    "family": "restricted_w_1.0",
    "rep": 36
  },
  {
    "alpha_hill": 1.6338397491201708,
    "xi": 0.386051399175265,
    "W1": 0.04765930254438898,
    "n_lifetimes": 507,
    "family": "restricted_w_1.0",
    "rep": 37
  },
  {
    "alpha_hill": 1.6824587435406346,
    "xi": 0.46279665753057386,
    "W1": 0.037104586803867884,
    "n_lifetimes": 506,
    "family": "restricted_w_1.0",
    "rep": 38
  },
  {
    "alpha_hill": 1.6842670401780855,
    "xi": 0.31003680794474164,
    "W1": 0.04364834666195121,
    "n_lifetimes": 500,
    "family": "restricted_w_1.0",
    "rep": 39
  },
  {
    "alpha_hill": 1.6354194605578904,
    "xi": 0.4632784572003384,
    "W1": 0.08075815381339913,
    "n_lifetimes": 498,
    "family": "restricted_w_1.0",
    "rep": 40
  },
  {
    "alpha_hill": 1.7222259955144898,
    "xi": 0.4187550747215255,
    "W1": 0.021239227015902792,
    "n_lifetimes": 506,
    "family": "restricted_w_1.0",
    "rep": 41
  },
  {
    "alpha_hill": 1.7579485897815097,
    "xi": 0.4288252918618163,
    "W1": 0.024707524740709585,
    "n_lifetimes": 506,
    "family": "restricted_w_1.0",
    "rep": 42
  },
  {
    "alpha_hill": 1.7497010586455721,
    "xi": 0.46498544824098553,
    "W1": 0.016628493857524566,
    "n_lifetimes": 506,
    "family": "restricted_w_1.0",
    "rep": 43
  },
  {
    "alpha_hill": 1.595271618407245,
    "xi": 0.36774758916362577,
    "W1": 0.10429004275373402,
    "n_lifetimes": 507,
    "family": "restricted_w_1.0",
    "rep": 44
  },
  {
    "alpha_hill": 1.6751667349354462,
    "xi": 0.5869894397473769,
    "W1": 0.01447507736430092,
    "n_lifetimes": 512,
    "family": "restricted_w_1.0",
    "rep": 45
  },
  {
    "alpha_hill": 1.4956795984050708,
    "xi": 0.3487853011675264,
    "W1": 0.09611020394416911,
    "n_lifetimes": 501,
    "family": "restricted_w_1.0",
    "rep": 46
  },
  {
    "alpha_hill": 1.9223316581964975,
    "xi": 0.3631801830075888,
    "W1": 0.06255618473616135,
    "n_lifetimes": 516,
    "family": "restricted_w_1.0",
    "rep": 47
  },
  {
    "alpha_hill": 1.7248732000533658,
    "xi": 0.437280020609472,
    "W1": 0.020226847763456277,
    "n_lifetimes": 506,
    "family": "restricted_w_1.0",
    "rep": 48
  },
  {
    "alpha_hill": 1.6482911562120008,
    "xi": 0.5688210663479325,
    "W1": 0.020961534773434792,
    "n_lifetimes": 481,
    "family": "restricted_w_1.0",
    "rep": 49
  },
  {
    "alpha_hill": 1.5785061311371704,
    "xi": 0.4417091280855831,
    "W1": 0.05029899483748218,
    "n_lifetimes": 522,
    "family": "restricted_w_2.0",
    "rep": 0
  },
  {
    "alpha_hill": 1.7457204216204767,
    "xi": 0.5153644325594857,
    "W1": 0.03935745915080309,
    "n_lifetimes": 495,
    "family": "restricted_w_2.0",
    "rep": 1
  },
  {
    "alpha_hill": 1.744673030794808,
    "xi": 0.582884467593304,
    "W1": 0.04379905236040278,
    "n_lifetimes": 487,
    "family": "restricted_w_2.0",
    "rep": 2
  },
  {
    "alpha_hill": 1.8860528802241443,
    "xi": 0.38261305635449117,
    "W1": 0.044715841520491906,
    "n_lifetimes": 499,
    "family": "restricted_w_2.0",
    "rep": 3
  },
  {
    "alpha_hill": 1.7073782699397204,
    "xi": 0.476029246377754,
    "W1": 0.050479511774931825,
    "n_lifetimes": 484,
    "family": "restricted_w_2.0",
    "rep": 4
  },
  {
    "alpha_hill": 1.8870694910576493,
    "xi": 0.2782331453953967,
    "W1": 0.05000318745140325,
    "n_lifetimes": 497,
    "family": "restricted_w_2.0",
    "rep": 5
  },
  {
    "alpha_hill": 1.6360637442320005,
    "xi": 0.3419053348348478,
    "W1": 0.020969533976891927,
    "n_lifetimes": 478,
    "family": "restricted_w_2.0",
    "rep": 6
  },
  {
    "alpha_hill": 1.6977256483457968,
    "xi": 0.3697907094885524,
    "W1": 0.028952801400108995,
    "n_lifetimes": 523,
    "family": "restricted_w_2.0",
    "rep": 7
  },
  {
    "alpha_hill": 1.9353312322422618,
    "xi": 0.3864811837501022,
    "W1": 0.01610648054970819,
    "n_lifetimes": 498,
    "family": "restricted_w_2.0",
    "rep": 8
  },
  {
    "alpha_hill": 1.6611817586944002,
    "xi": 0.5946335142824287,
    "W1": 0.020224478022726942,
    "n_lifetimes": 496,
    "family": "restricted_w_2.0",
    "rep": 9
  },
  {
    "alpha_hill": 1.721133681906896,
    "xi": 0.5353217128614105,
    "W1": 0.070821322797054,
    "n_lifetimes": 499,
    "family": "restricted_w_2.0",
    "rep": 10
  },
  {
    "alpha_hill": 1.714821633806117,
    "xi": 0.3969484904865844,
    "W1": 0.04772146648138639,
    "n_lifetimes": 499,
    "family": "restricted_w_2.0",
    "rep": 11
  },
  {
    "alpha_hill": 1.8062416724580097,
    "xi": 0.4658074460173289,
    "W1": 0.02249322269851447,
    "n_lifetimes": 494,
    "family": "restricted_w_2.0",
    "rep": 12
  },
  {
    "alpha_hill": 1.702002991475575,
    "xi": 0.29751320201744336,
    "W1": 0.036609309397217044,
    "n_lifetimes": 505,
    "family": "restricted_w_2.0",
    "rep": 13
  },
  {
    "alpha_hill": 1.9259992403965205,
    "xi": 0.3706890367876981,
    "W1": 0.02111269974797175,
    "n_lifetimes": 492,
    "family": "restricted_w_2.0",
    "rep": 14
  },
  {
    "alpha_hill": 1.8781457496006513,
    "xi": 0.42132364121378607,
    "W1": 0.08766023631216377,
    "n_lifetimes": 500,
    "family": "restricted_w_2.0",
    "rep": 15
  },
  {
    "alpha_hill": 1.6729781040914353,
    "xi": 0.4378653554042482,
    "W1": 0.016212300899524856,
    "n_lifetimes": 501,
    "family": "restricted_w_2.0",
    "rep": 16
  },
  {
    "alpha_hill": 1.5298623458560614,
    "xi": 0.4436145520297867,
    "W1": 0.028895354793321566,
    "n_lifetimes": 480,
    "family": "restricted_w_2.0",
    "rep": 17
  },
  {
    "alpha_hill": 1.7328890533139771,
    "xi": 0.5813535631250697,
    "W1": 0.06863462423254388,
    "n_lifetimes": 505,
    "family": "restricted_w_2.0",
    "rep": 18
  },
  {
    "alpha_hill": 1.6486150317758987,
    "xi": 0.5223699961585184,
    "W1": 0.0623093373518065,
    "n_lifetimes": 514,
    "family": "restricted_w_2.0",
    "rep": 19
  },
  {
    "alpha_hill": 1.6628170588479778,
    "xi": 0.45735736558882145,
    "W1": 0.026838215123905412,
    "n_lifetimes": 503,
    "family": "restricted_w_2.0",
    "rep": 20
  },
  {
    "alpha_hill": 1.6248521508181288,
    "xi": 0.4921112133026384,
    "W1": 0.11674190988032837,
    "n_lifetimes": 490,
    "family": "restricted_w_2.0",
    "rep": 21
  },
  {
    "alpha_hill": 1.6605048099903539,
    "xi": 0.354565143007173,
    "W1": 0.01652069543240583,
    "n_lifetimes": 485,
    "family": "restricted_w_2.0",
    "rep": 22
  },
  {
    "alpha_hill": 1.7636150760990268,
    "xi": 0.46626855199323114,
    "W1": 0.06291204045906394,
    "n_lifetimes": 486,
    "family": "restricted_w_2.0",
    "rep": 23
  },
  {
    "alpha_hill": 1.5522106371335676,
    "xi": 0.5168027811771698,
    "W1": 0.028582841512095218,
    "n_lifetimes": 492,
    "family": "restricted_w_2.0",
    "rep": 24
  },
  {
    "alpha_hill": 1.6520567507944905,
    "xi": 0.5752399606568641,
    "W1": 0.09930648771713194,
    "n_lifetimes": 481,
    "family": "restricted_w_2.0",
    "rep": 25
  },
  {
    "alpha_hill": 1.9167009902013556,
    "xi": 0.32628740155616315,
    "W1": 0.019865115518986752,
    "n_lifetimes": 507,
    "family": "restricted_w_2.0",
    "rep": 26
  },
  {
    "alpha_hill": 1.456248079610958,
    "xi": 0.5022298667049455,
    "W1": 0.14396083959350947,
    "n_lifetimes": 487,
    "family": "restricted_w_2.0",
    "rep": 27
  },
  {
    "alpha_hill": 1.6082062786239135,
    "xi": 0.431675831466083,
    "W1": 0.03551146672875637,
    "n_lifetimes": 491,
    "family": "restricted_w_2.0",
    "rep": 28
  },
  {
    "alpha_hill": 1.6973290192284474,
    "xi": 0.5050492242546157,
    "W1": 0.03544563449846422,
    "n_lifetimes": 512,
    "family": "restricted_w_2.0",
    "rep": 29
  },
  {
    "alpha_hill": 1.5751013902131261,
    "xi": 0.4534539274343346,
    "W1": 0.0567919745887142,
    "n_lifetimes": 492,
    "family": "restricted_w_2.0",
    "rep": 30
  },
  {
    "alpha_hill": 1.7153110401176717,
    "xi": 0.41415824115468314,
    "W1": 0.021095191959810234,
    "n_lifetimes": 493,
    "family": "restricted_w_2.0",
    "rep": 31
  },
  {
    "alpha_hill": 1.6376659428642624,
    "xi": 0.4884721287914572,
    "W1": 0.01943936659936331,
    "n_lifetimes": 523,
    "family": "restricted_w_2.0",
    "rep": 32
  },
  {
    "alpha_hill": 1.8328672380114095,
    "xi": 0.3895313865756198,
    "W1": 0.031025465441088862,
    "n_lifetimes": 493,
    "family": "restricted_w_2.0",
    "rep": 33
  },
  {
    "alpha_hill": 1.822929877900858,
    "xi": 0.33562711843531706,
    "W1": 0.021820555707713962,
    "n_lifetimes": 505,
    "family": "restricted_w_2.0",
    "rep": 34
  },
  {
    "alpha_hill": 1.8189161406122356,
    "xi": 0.4013777698927207,
    "W1": 0.05282584182736558,
    "n_lifetimes": 493,
    "family": "restricted_w_2.0",
    "rep": 35
  },
  {
    "alpha_hill": 1.5374943900508835,
    "xi": 0.505661486680006,
    "W1": 0.01738829082825808,
    "n_lifetimes": 508,
    "family": "restricted_w_2.0",
    "rep": 36
  },
  {
    "alpha_hill": 1.920575843656259,
    "xi": 0.28003248250947654,
    "W1": 0.03691351739892465,
    "n_lifetimes": 490,
    "family": "restricted_w_2.0",
    "rep": 37
  },
  {
    "alpha_hill": 1.5974527092980835,
    "xi": 0.39883620372400885,
    "W1": 0.04242421329369915,
    "n_lifetimes": 485,
    "family": "restricted_w_2.0",
    "rep": 38
  },
  {
    "alpha_hill": 1.7322432462046706,
    "xi": 0.465206008658524,
    "W1": 0.06158170335754014,
    "n_lifetimes": 502,
    "family": "restricted_w_2.0",
    "rep": 39
  },
  {
    "alpha_hill": 1.5655935300601274,
    "xi": 0.5439693562117109,
    "W1": 0.07586920662606797,
    "n_lifetimes": 503,
    "family": "restricted_w_2.0",
    "rep": 40
  },
  {
    "alpha_hill": 1.7524586619265266,
    "xi": 0.40968944310487443,
    "W1": 0.02332390732839732,
    "n_lifetimes": 505,
    "family": "restricted_w_2.0",
    "rep": 41
  },
  {
    "alpha_hill": 1.639716092702657,
    "xi": 0.3896172201971937,
    "W1": 0.023044667843466364,
    "n_lifetimes": 508,
    "family": "restricted_w_2.0",
    "rep": 42
  },
  {
    "alpha_hill": 1.734905542429957,
    "xi": 0.4546229596786959,
    "W1": 0.030608535648337563,
    "n_lifetimes": 513,
    "family": "restricted_w_2.0",
    "rep": 43
  },
  {
    "alpha_hill": 1.641082356960289,
    "xi": 0.4677853500063188,
    "W1": 0.06371215015448815,
    "n_lifetimes": 486,
    "family": "restricted_w_2.0",
    "rep": 44
  },
  {
    "alpha_hill": 1.8869877811069298,
    "xi": 0.2572435161743233,
    "W1": 0.02766619571691051,
    "n_lifetimes": 505,
    "family": "restricted_w_2.0",
    "rep": 45
  },
  {
    "alpha_hill": 1.637986258240187,
    "xi": 0.5121847377851965,
    "W1": 0.03748910680174114,
    "n_lifetimes": 487,
    "family": "restricted_w_2.0",
    "rep": 46
  },
  {
    "alpha_hill": 1.6062951192148356,
    "xi": 0.4393962941298025,
    "W1": 0.16799570194821783,
    "n_lifetimes": 514,
    "family": "restricted_w_2.0",
    "rep": 47
  },
  {
    "alpha_hill": 1.7722093966159853,
    "xi": 0.3363046368771272,
    "W1": 0.02346373396283027,
    "n_lifetimes": 525,
    "family": "restricted_w_2.0",
    "rep": 48
  },
  {
    "alpha_hill": 1.7018848195406764,
    "xi": 0.5278015733325436,
    "W1": 0.020275169475822717,
    "n_lifetimes": 502,
    "family": "restricted_w_2.0",
    "rep": 49
  },
  {
    "alpha_hill": 1.5539891912125143,
    "xi": 0.4976441686486923,
    "W1": 0.020235359188556564,
    "n_lifetimes": 481,
    "family": "restricted_w_4.0",
    "rep": 0
  },
  {
    "alpha_hill": 2.1138078575671533,
    "xi": 0.3111361627180916,
    "W1": 0.03645190959433834,
    "n_lifetimes": 506,
    "family": "restricted_w_4.0",
    "rep": 1
  },
  {
    "alpha_hill": 1.60653318305224,
    "xi": 0.6320397745848083,
    "W1": 0.015637498620703794,
    "n_lifetimes": 498,
    "family": "restricted_w_4.0",
    "rep": 2
  },
  {
    "alpha_hill": 1.7304190397491193,
    "xi": 0.23396465088980337,
    "W1": 0.07057917474369424,
    "n_lifetimes": 495,
    "family": "restricted_w_4.0",
    "rep": 3
  },
  {
    "alpha_hill": 1.5829782519707973,
    "xi": 0.2866595885978942,
    "W1": 0.054982116273380566,
    "n_lifetimes": 492,
    "family": "restricted_w_4.0",
    "rep": 4
  },
  {
    "alpha_hill": 1.7099320934833304,
    "xi": 0.46202306304054874,
    "W1": 0.037665593970474406,
    "n_lifetimes": 492,
    "family": "restricted_w_4.0",
    "rep": 5
  },
  {
    "alpha_hill": 1.6820017869766164,
    "xi": 0.32984365621876643,
    "W1": 0.03795302853298309,
    "n_lifetimes": 514,
    "family": "restricted_w_4.0",
    "rep": 6
  },
  {
    "alpha_hill": 1.903710705156091,
    "xi": 0.25786502401688716,
    "W1": 0.02150924415934629,
    "n_lifetimes": 490,
    "family": "restricted_w_4.0",
    "rep": 7
  },
  {
    "alpha_hill": 1.9916686166615674,
    "xi": 0.385581937596581,
    "W1": 0.04094018325478596,
    "n_lifetimes": 496,
    "family": "restricted_w_4.0",
    "rep": 8
  },
  {
    "alpha_hill": 1.6308318206225234,
    "xi": 0.45397936555430624,
    "W1": 0.0587598426110586,
    "n_lifetimes": 508,
    "family": "restricted_w_4.0",
    "rep": 9
  },
  {
    "alpha_hill": 1.730706019456523,
    "xi": 0.4784027986260426,
    "W1": 0.02445290754901233,
    "n_lifetimes": 511,
    "family": "restricted_w_4.0",
    "rep": 10
  },
  {
    "alpha_hill": 1.7397860017202635,
    "xi": 0.5198857255940341,
    "W1": 0.016882546827495196,
    "n_lifetimes": 504,
    "family": "restricted_w_4.0",
    "rep": 11
  },
  {
    "alpha_hill": 1.8492677933298958,
    "xi": 0.48177472173559377,
    "W1": 0.021955616319147768,
    "n_lifetimes": 499,
    "family": "restricted_w_4.0",
    "rep": 12
  },
  {
    "alpha_hill": 1.914140808733931,
    "xi": 0.45573056774162535,
    "W1": 0.024707464545784107,
    "n_lifetimes": 496,
    "family": "restricted_w_4.0",
    "rep": 13
  },
  {
    "alpha_hill": 1.8401836005805823,
    "xi": 0.4120724987082258,
    "W1": 0.08047016465046632,
    "n_lifetimes": 498,
    "family": "restricted_w_4.0",
    "rep": 14
  },
  {
    "alpha_hill": 1.6180983499092036,
    "xi": 0.5651214279475463,
    "W1": 0.029618645605983502,
    "n_lifetimes": 487,
    "family": "restricted_w_4.0",
    "rep": 15
  },
  {
    "alpha_hill": 1.8835164104492772,
    "xi": 0.4101127483151648,
    "W1": 0.028828324716894567,
    "n_lifetimes": 506,
    "family": "restricted_w_4.0",
    "rep": 16
  },
  {
    "alpha_hill": 1.521487343429936,
    "xi": 0.42052684650373007,
    "W1": 0.021074344079064482,
    "n_lifetimes": 502,
    "family": "restricted_w_4.0",
    "rep": 17
  },
  {
    "alpha_hill": 1.8669436221914872,
    "xi": 0.32300964260962384,
    "W1": 0.017691196560801797,
    "n_lifetimes": 479,
    "family": "restricted_w_4.0",
    "rep": 18
  },
  {
    "alpha_hill": 1.6041787620224115,
    "xi": 0.4292228527725539,
    "W1": 0.041455333237379,
    "n_lifetimes": 501,
    "family": "restricted_w_4.0",
    "rep": 19
  },
  {
    "alpha_hill": 1.892498530259727,
    "xi": 0.21907699588634572,
    "W1": 0.031736684042543845,
    "n_lifetimes": 483,
    "family": "restricted_w_4.0",
    "rep": 20
  },
  {
    "alpha_hill": 1.8656753156281973,
    "xi": 0.48046877435575547,
    "W1": 0.02301363349372962,
    "n_lifetimes": 499,
    "family": "restricted_w_4.0",
    "rep": 21
  },
  {
    "alpha_hill": 1.7164729048993848,
    "xi": 0.38332456662826275,
    "W1": 0.11040485616247439,
    "n_lifetimes": 516,
    "family": "restricted_w_4.0",
    "rep": 22
  },
  {
    "alpha_hill": 1.392952770974797,
    "xi": 0.4926494335626258,
    "W1": 0.044371921580214066,
    "n_lifetimes": 494,
    "family": "restricted_w_4.0",
    "rep": 23
  },
  {
    "alpha_hill": 1.4900316032945413,
    "xi": 0.7016571039612467,
    "W1": 0.037707892291440975,
    "n_lifetimes": 475,
    "family": "restricted_w_4.0",
    "rep": 24
  },
  {
    "alpha_hill": 1.6118667938621618,
    "xi": 0.4613326061823533,
    "W1": 0.02079676929049238,
    "n_lifetimes": 504,
    "family": "restricted_w_4.0",
    "rep": 25
  },
  {
    "alpha_hill": 1.7452944914356028,
    "xi": 0.5668745622016637,
    "W1": 0.03550739360703746,
    "n_lifetimes": 496,
    "family": "restricted_w_4.0",
    "rep": 26
  },
  {
    "alpha_hill": 1.7822023375223515,
    "xi": 0.4076887063325725,
    "W1": 0.029623238562892173,
    "n_lifetimes": 481,
    "family": "restricted_w_4.0",
    "rep": 27
  },
  {
    "alpha_hill": 2.032896357696919,
    "xi": 0.3361631890700437,
    "W1": 0.06002355996193556,
    "n_lifetimes": 497,
    "family": "restricted_w_4.0",
    "rep": 28
  },
  {
    "alpha_hill": 1.8192911993413774,
    "xi": 0.6017029160227318,
    "W1": 0.018392055895637527,
    "n_lifetimes": 505,
    "family": "restricted_w_4.0",
    "rep": 29
  },
  {
    "alpha_hill": 1.5970029358592344,
    "xi": 0.4569527549360553,
    "W1": 0.01667984326156697,
    "n_lifetimes": 507,
    "family": "restricted_w_4.0",
    "rep": 30
  },
  {
    "alpha_hill": 1.4905629845608217,
    "xi": 0.4793781312212204,
    "W1": 0.1297467818265176,
    "n_lifetimes": 484,
    "family": "restricted_w_4.0",
    "rep": 31
  },
  {
    "alpha_hill": 1.9557336001454033,
    "xi": 0.3759349740054898,
    "W1": 0.022976054086915183,
    "n_lifetimes": 501,
    "family": "restricted_w_4.0",
    "rep": 32
  },
  {
    "alpha_hill": 1.6421724543094929,
    "xi": 0.5184671881865441,
    "W1": 0.017114005834396845,
    "n_lifetimes": 495,
    "family": "restricted_w_4.0",
    "rep": 33
  },
  {
    "alpha_hill": 1.7713942762561086,
    "xi": 0.5061356047943857,
    "W1": 0.018670583980185475,
    "n_lifetimes": 493,
    "family": "restricted_w_4.0",
    "rep": 34
  },
  {
    "alpha_hill": 2.048224735975399,
    "xi": 0.3466448396738957,
    "W1": 0.019370689386429156,
    "n_lifetimes": 489,
    "family": "restricted_w_4.0",
    "rep": 35
  },
  {
    "alpha_hill": 1.6056738572400533,
    "xi": 0.4923618717004149,
    "W1": 0.0300916459255265,
    "n_lifetimes": 524,
    "family": "restricted_w_4.0",
    "rep": 36
  },
  {
    "alpha_hill": 1.9134135616157115,
    "xi": 0.37602733742496586,
    "W1": 0.020772116995616735,
    "n_lifetimes": 510,
    "family": "restricted_w_4.0",
    "rep": 37
  },
  {
    "alpha_hill": 2.007431356062614,
    "xi": 0.38131270452029464,
    "W1": 0.055869213710758384,
    "n_lifetimes": 492,
    "family": "restricted_w_4.0",
    "rep": 38
  },
  {
    "alpha_hill": 1.6138330300905301,
    "xi": 0.5331089506872824,
    "W1": 0.022149462946458594,
    "n_lifetimes": 520,
    "family": "restricted_w_4.0",
    "rep": 39
  },
  {
    "alpha_hill": 1.5524003015489074,
    "xi": 0.5445587853899851,
    "W1": 0.009125842637350268,
    "n_lifetimes": 497,
    "family": "restricted_w_4.0",
    "rep": 40
  },
  {
    "alpha_hill": 1.654068032830148,
    "xi": 0.3672926929460381,
    "W1": 0.010463026905489097,
    "n_lifetimes": 488,
    "family": "restricted_w_4.0",
    "rep": 41
  },
  {
    "alpha_hill": 1.7227725191578342,
    "xi": 0.5041053809966334,
    "W1": 0.02128812732520014,
    "n_lifetimes": 498,
    "family": "restricted_w_4.0",
    "rep": 42
  },
  {
    "alpha_hill": 1.6820580745945142,
    "xi": 0.35697110062744125,
    "W1": 0.023444747329425607,
    "n_lifetimes": 499,
    "family": "restricted_w_4.0",
    "rep": 43
  },
  {
    "alpha_hill": 1.8209230798599578,
    "xi": 0.4721725828118488,
    "W1": 0.025792109283155937,
    "n_lifetimes": 499,
    "family": "restricted_w_4.0",
    "rep": 44
  },
  {
    "alpha_hill": 1.8191257212114829,
    "xi": 0.3465193118332356,
    "W1": 0.04836958215284753,
    "n_lifetimes": 516,
    "family": "restricted_w_4.0",
    "rep": 45
  },
  {
    "alpha_hill": 1.7099507933208067,
    "xi": 0.4710508255085906,
    "W1": 0.016611811588450168,
    "n_lifetimes": 498,
    "family": "restricted_w_4.0",
    "rep": 46
  },
  {
    "alpha_hill": 1.7283681806438638,
    "xi": 0.4570465640190504,
    "W1": 0.05771121389083979,
    "n_lifetimes": 510,
    "family": "restricted_w_4.0",
    "rep": 47
  },
  {
    "alpha_hill": 1.8744046006414132,
    "xi": 0.15660729873609439,
    "W1": 0.05510494757036928,
    "n_lifetimes": 501,
    "family": "restricted_w_4.0",
    "rep": 48
  },
  {
    "alpha_hill": 2.1151801586935775,
    "xi": 0.4011570207782932,
    "W1": 0.015639019988825047,
    "n_lifetimes": 495,
    "family": "restricted_w_4.0",
    "rep": 49
  },
  {
    "alpha_hill": 1.8403015263671312,
    "xi": 0.4581639334828108,
    "W1": 0.018484917103469833,
    "n_lifetimes": 496,
    "family": "mixed_60r_w1.0_f0.5",
    "rep": 0
  },
  {
    "alpha_hill": 1.870489027916081,
    "xi": 0.4407978173788326,
    "W1": 0.0191731973775865,
    "n_lifetimes": 501,
    "family": "mixed_60r_w1.0_f0.5",
    "rep": 1
  },
  {
    "alpha_hill": 1.7226717864020935,
    "xi": 0.3867102788732134,
    "W1": 0.053963908245038605,
    "n_lifetimes": 505,
    "family": "mixed_60r_w1.0_f0.5",
    "rep": 2
  },
  {
    "alpha_hill": 1.4964079696839625,
    "xi": 0.4524248690680932,
    "W1": 0.012231281221513537,
    "n_lifetimes": 503,
    "family": "mixed_60r_w1.0_f0.5",
    "rep": 3
  },
  {
    "alpha_hill": 1.8414016595930212,
    "xi": 0.38476688805467163,
    "W1": 0.10633827716134989,
    "n_lifetimes": 494,
    "family": "mixed_60r_w1.0_f0.5",
    "rep": 4
  },
  {
    "alpha_hill": 1.6390452343386983,
    "xi": 0.4273684290850706,
    "W1": 0.019185730396837165,
    "n_lifetimes": 514,
    "family": "mixed_60r_w1.0_f0.5",
    "rep": 5
  },
  {
    "alpha_hill": 1.6560674185934594,
    "xi": 0.4538404975374116,
    "W1": 0.01098678781411922,
    "n_lifetimes": 516,
    "family": "mixed_60r_w1.0_f0.5",
    "rep": 6
  },
  {
    "alpha_hill": 1.6686139451073199,
    "xi": 0.41073530390021734,
    "W1": 0.027425318337430747,
    "n_lifetimes": 516,
    "family": "mixed_60r_w1.0_f0.5",
    "rep": 7
  },
  {
    "alpha_hill": 1.4994992099554634,
    "xi": 0.7034438881461498,
    "W1": 0.018714358929814524,
    "n_lifetimes": 508,
    "family": "mixed_60r_w1.0_f0.5",
    "rep": 8
  },
  {
    "alpha_hill": 1.5742981874525803,
    "xi": 0.6301153446748353,
    "W1": 0.017429663830892093,
    "n_lifetimes": 493,
    "family": "mixed_60r_w1.0_f0.5",
    "rep": 9
  },
  {
    "alpha_hill": 1.654531829809557,
    "xi": 0.4470466629783684,
    "W1": 0.033006968644265666,
    "n_lifetimes": 503,
    "family": "mixed_60r_w1.0_f0.5",
    "rep": 10
  },
  {
    "alpha_hill": 1.8281686316372385,
    "xi": 0.3585723459147609,
    "W1": 0.08228540702314971,
    "n_lifetimes": 508,
    "family": "mixed_60r_w1.0_f0.5",
    "rep": 11
  },
  {
    "alpha_hill": 1.4702764818193872,
    "xi": 0.4752674293641306,
    "W1": 0.012236954697704663,
    "n_lifetimes": 481,
    "family": "mixed_60r_w1.0_f0.5",
    "rep": 12
  },
  {
    "alpha_hill": 1.8513121814309517,
    "xi": 0.38498457876193964,
    "W1": 0.0287094175621019,
    "n_lifetimes": 495,
    "family": "mixed_60r_w1.0_f0.5",
    "rep": 13
  },
  {
    "alpha_hill": 1.6862305707847394,
    "xi": 0.501429864913846,
    "W1": 0.0917709328235295,
    "n_lifetimes": 476,
    "family": "mixed_60r_w1.0_f0.5",
    "rep": 14
  },
  {
    "alpha_hill": 1.63092412422103,
    "xi": 0.49998374075280483,
    "W1": 0.11380353325135897,
    "n_lifetimes": 482,
    "family": "mixed_60r_w1.0_f0.5",
    "rep": 15
  },
  {
    "alpha_hill": 1.7223486409775228,
    "xi": 0.4687096188099206,
    "W1": 0.05884123074532549,
    "n_lifetimes": 495,
    "family": "mixed_60r_w1.0_f0.5",
    "rep": 16
  },
  {
    "alpha_hill": 1.656664200705077,
    "xi": 0.30559602056696733,
    "W1": 0.02582989334341901,
    "n_lifetimes": 505,
    "family": "mixed_60r_w1.0_f0.5",
    "rep": 17
  },
  {
    "alpha_hill": 1.5783907580092695,
    "xi": 0.5050667792958317,
    "W1": 0.012864817229780268,
    "n_lifetimes": 511,
    "family": "mixed_60r_w1.0_f0.5",
    "rep": 18
  },
  {
    "alpha_hill": 1.6636865555833695,
    "xi": 0.46201919235167677,
    "W1": 0.07245785118253947,
    "n_lifetimes": 490,
    "family": "mixed_60r_w1.0_f0.5",
    "rep": 19
  },
  {
    "alpha_hill": 1.8078761185266379,
    "xi": 0.37511644706373587,
    "W1": 0.04046498284275569,
    "n_lifetimes": 493,
    "family": "mixed_60r_w1.0_f0.5",
    "rep": 20
  },
  {
    "alpha_hill": 1.6069178365240624,
    "xi": 0.48911162238462097,
    "W1": 0.012469308353954385,
    "n_lifetimes": 476,
    "family": "mixed_60r_w1.0_f0.5",
    "rep": 21
  },
  {
    "alpha_hill": 1.665570285076025,
    "xi": 0.4001289145555328,
    "W1": 0.03506169590208244,
    "n_lifetimes": 503,
    "family": "mixed_60r_w1.0_f0.5",
    "rep": 22
  },
  {
    "alpha_hill": 1.6525694461414315,
    "xi": 0.3634020850957294,
    "W1": 0.00916987090018041,
    "n_lifetimes": 497,
    "family": "mixed_60r_w1.0_f0.5",
    "rep": 23
  },
  {
    "alpha_hill": 1.6859171572917608,
    "xi": 0.4701874207536303,
    "W1": 0.08878009477718307,
    "n_lifetimes": 489,
    "family": "mixed_60r_w1.0_f0.5",
    "rep": 24
  },
  {
    "alpha_hill": 1.6976393361504496,
    "xi": 0.357420809460016,
    "W1": 0.03774306816942885,
    "n_lifetimes": 487,
    "family": "mixed_60r_w1.0_f0.5",
    "rep": 25
  },
  {
    "alpha_hill": 1.712032528470765,
    "xi": 0.4722242168103995,
    "W1": 0.030122905712216624,
    "n_lifetimes": 515,
    "family": "mixed_60r_w1.0_f0.5",
    "rep": 26
  },
  {
    "alpha_hill": 1.5438278718926222,
    "xi": 0.457494643309067,
    "W1": 0.01115248958869976,
    "n_lifetimes": 496,
    "family": "mixed_60r_w1.0_f0.5",
    "rep": 27
  },
  {
    "alpha_hill": 1.6709624822456437,
    "xi": 0.33017548670709207,
    "W1": 0.03200769483205072,
    "n_lifetimes": 503,
    "family": "mixed_60r_w1.0_f0.5",
    "rep": 28
  },
  {
    "alpha_hill": 1.6388424702203805,
    "xi": 0.4977756270411562,
    "W1": 0.019716428933423617,
    "n_lifetimes": 507,
    "family": "mixed_60r_w1.0_f0.5",
    "rep": 29
  },
  {
    "alpha_hill": 1.563223662608397,
    "xi": 0.5094917643078668,
    "W1": 0.013800448399242663,
    "n_lifetimes": 480,
    "family": "mixed_60r_w1.0_f0.5",
    "rep": 30
  },
  {
    "alpha_hill": 2.047091651876058,
    "xi": 0.43235583519025667,
    "W1": 0.07601081651636134,
    "n_lifetimes": 505,
    "family": "mixed_60r_w1.0_f0.5",
    "rep": 31
  },
  {
    "alpha_hill": 1.5264026617122828,
    "xi": 0.5155487505899137,
    "W1": 0.016654927093426607,
    "n_lifetimes": 503,
    "family": "mixed_60r_w1.0_f0.5",
    "rep": 32
  },
  {
    "alpha_hill": 1.7017044609169834,
    "xi": 0.5752848496167191,
    "W1": 0.04885707410024348,
    "n_lifetimes": 509,
    "family": "mixed_60r_w1.0_f0.5",
    "rep": 33
  },
  {
    "alpha_hill": 1.7692752186241831,
    "xi": 0.5281709143171558,
    "W1": 0.027354511168852923,
    "n_lifetimes": 518,
    "family": "mixed_60r_w1.0_f0.5",
    "rep": 34
  },
  {
    "alpha_hill": 1.654990917842527,
    "xi": 0.4281965679589498,
    "W1": 0.044388438247321846,
    "n_lifetimes": 508,
    "family": "mixed_60r_w1.0_f0.5",
    "rep": 35
  },
  {
    "alpha_hill": 1.5891212625362154,
    "xi": 0.5938798712761109,
    "W1": 0.02940849542235227,
    "n_lifetimes": 504,
    "family": "mixed_60r_w1.0_f0.5",
    "rep": 36
  },
  {
    "alpha_hill": 1.6687518056073092,
    "xi": 0.5370427841052314,
    "W1": 0.01783659841115771,
    "n_lifetimes": 508,
    "family": "mixed_60r_w1.0_f0.5",
    "rep": 37
  },
  {
    "alpha_hill": 1.628719024364621,
    "xi": 0.5138742369345383,
    "W1": 0.017100558039969724,
    "n_lifetimes": 497,
    "family": "mixed_60r_w1.0_f0.5",
    "rep": 38
  },
  {
    "alpha_hill": 1.6777038588008937,
    "xi": 0.44943143318022594,
    "W1": 0.028318463917134877,
    "n_lifetimes": 505,
    "family": "mixed_60r_w1.0_f0.5",
    "rep": 39
  },
  {
    "alpha_hill": 1.5269254693112777,
    "xi": 0.48584655322639037,
    "W1": 0.04721313770396651,
    "n_lifetimes": 497,
    "family": "mixed_60r_w1.0_f0.5",
    "rep": 40
  },
  {
    "alpha_hill": 1.662632931718686,
    "xi": 0.44277917805593303,
    "W1": 0.042913263070902166,
    "n_lifetimes": 508,
    "family": "mixed_60r_w1.0_f0.5",
    "rep": 41
  },
  {
    "alpha_hill": 1.3838940992613151,
    "xi": 0.6015921875812582,
    "W1": 0.029533928203120237,
    "n_lifetimes": 502,
    "family": "mixed_60r_w1.0_f0.5",
    "rep": 42
  },
  {
    "alpha_hill": 1.6852079653917196,
    "xi": 0.5270065147023826,
    "W1": 0.06302034423810035,
    "n_lifetimes": 504,
    "family": "mixed_60r_w1.0_f0.5",
    "rep": 43
  },
  {
    "alpha_hill": 1.4600008072165522,
    "xi": 0.5118518141593154,
    "W1": 0.04456318041700757,
    "n_lifetimes": 520,
    "family": "mixed_60r_w1.0_f0.5",
    "rep": 44
  },
  {
    "alpha_hill": 2.0279115006599073,
    "xi": 0.3365595251336103,
    "W1": 0.016464350931540934,
    "n_lifetimes": 496,
    "family": "mixed_60r_w1.0_f0.5",
    "rep": 45
  },
  {
    "alpha_hill": 1.8058129699669365,
    "xi": 0.4604382699552263,
    "W1": 0.03753642571135123,
    "n_lifetimes": 498,
    "family": "mixed_60r_w1.0_f0.5",
    "rep": 46
  },
  {
    "alpha_hill": 1.3909260347399002,
    "xi": 0.49710374608875874,
    "W1": 0.06549207054227076,
    "n_lifetimes": 472,
    "family": "mixed_60r_w1.0_f0.5",
    "rep": 47
  },
  {
    "alpha_hill": 1.58112322647005,
    "xi": 0.45001723204613114,
    "W1": 0.015309561213436395,
    "n_lifetimes": 520,
    "family": "mixed_60r_w1.0_f0.5",
    "rep": 48
  },
  {
    "alpha_hill": 1.9632233583884238,
    "xi": 0.4593658215881443,
    "W1": 0.016591954598827303,
    "n_lifetimes": 487,
    "family": "mixed_60r_w1.0_f0.5",
    "rep": 49
  }
]